mov_avg_filter/MavgFilter.sv
`default_nettype none

module MavgFilter #(
    parameter COEFF_BITS = 8,
    parameter INPUT_BITS = 16,
    parameter OUTPUT_BITS = 32
) (
    input logic clk_i,
    input logic rst_i,
    input logic signed [INPUT_BITS-1:0] original_data,
    output logic signed [OUTPUT_BITS-1:0] filtered_data
);

logic signed [COEFF_BITS-1:0] b [7:0];
logic signed [INPUT_BITS-1:0] sample [6:0];


generate
    genvar i;
    for (i = 0; i < 8; i++) begin
        assign  b[i] = 8'b00010000;
    end
endgenerate
    
always_ff @( posedge clk_i ) begin
    if (rst_i == 1'b0) begin
        sample[0] <= '0;
        sample[1] <= '0;
        sample[2] <= '0;
        sample[3] <= '0;
        sample[4] <= '0;
        sample[5] <= '0;
        sample[6] <= '0;
    end else begin
        sample[0] <= original_data;
        sample[1] <= sample[0];
        sample[2] <= sample[1];
        sample[3] <= sample[2];
        sample[4] <= sample[3];
        sample[5] <= sample[4];
        sample[6] <= sample[5];
    end
end

assign filtered_data = (b[0] * original_data) +
                       (b[1] * sample[0]) +
                       (b[2] * sample[1]) +
                       (b[3] * sample[2]) +
                       (b[4] * sample[3]) +
                       (b[5] * sample[4]) +
                       (b[6] * sample[5]) +
                       (b[7] * sample[6]) ;
endmodule

mov_avg_filter/fir_filter_mavg_tb.sv
`timescale 1ns/1ps

module fir_filter_mavg_tb();

localparam CLOCKPERIOD = 100;
localparam COEFF_BITS = 8;
localparam INPUT_BITS = 16;
localparam OUTPUT_BITS = 32;
localparam max_data = 1000;

logic clk_i, rst_i;
integer i,j;
logic signed [INPUT_BITS-1:0] data [max_data-1:0];
logic signed [INPUT_BITS-1:0] data_in;
logic signed [OUTPUT_BITS-1:0] data_out;


initial clk_i = 1'b0;
initial rst_i = 1'b0;

always begin
    #(CLOCKPERIOD/2) clk_i = ~clk_i;
end
initial begin
    #(CLOCKPERIOD*20);
    rst_i = 1'b1;
end

initial begin
    $readmemb("original.data", data);
    i = 0;
    forever begin
        @(posedge clk_i);
        if (rst_i) begin
            data_in = data[i];
            i = i+1;
        end
    end
end

initial begin
    integer file;
    file = $fopen("filtered.data");
    j = 0;
    forever begin
        @(posedge clk_i);
        if (rst_i) begin
            $fdisplay(file, "%b", data_out);
        end
    end
    $fclose(file);
end

MavgFilter #(
    .COEFF_BITS(COEFF_BITS),
    .INPUT_BITS(INPUT_BITS),
    .OUTPUT_BITS(OUTPUT_BITS)
    ) fir_filter (
        .clk_i,
        .rst_i,
        .original_data(data_in),
        .filtered_data(data_out)
    );

initial begin
    $dumpfile("fir.vcd");
    $dumpvars;
    #(CLOCKPERIOD*1021);
    $finish;
end

endmodule

mov_avg_filter/fir.vcd
$date
	Fri Jan 23 12:15:08 2026
$end
$version
	Icarus Verilog
$end
$timescale
	1ps
$end
$scope module fir_filter_mavg_tb $end
$var wire 32 ! data_out [31:0] $end
$var parameter 32 " CLOCKPERIOD $end
$var parameter 32 # COEFF_BITS $end
$var parameter 32 $ INPUT_BITS $end
$var parameter 32 % OUTPUT_BITS $end
$var parameter 32 & max_data $end
$var reg 1 ' clk_i $end
$var reg 16 ( data_in [15:0] $end
$var reg 1 ) rst_i $end
$var integer 32 * i [31:0] $end
$var integer 32 + j [31:0] $end
$scope module fir_filter $end
$var wire 1 ' clk_i $end
$var wire 16 , original_data [15:0] $end
$var wire 1 ) rst_i $end
$var wire 32 - filtered_data [31:0] $end
$var parameter 32 . COEFF_BITS $end
$var parameter 32 / INPUT_BITS $end
$var parameter 32 0 OUTPUT_BITS $end
$scope begin genblk1[0] $end
$var parameter 2 1 i $end
$upscope $end
$scope begin genblk1[1] $end
$var parameter 2 2 i $end
$upscope $end
$scope begin genblk1[2] $end
$var parameter 3 3 i $end
$upscope $end
$scope begin genblk1[3] $end
$var parameter 3 4 i $end
$upscope $end
$scope begin genblk1[4] $end
$var parameter 4 5 i $end
$upscope $end
$scope begin genblk1[5] $end
$var parameter 4 6 i $end
$upscope $end
$scope begin genblk1[6] $end
$var parameter 4 7 i $end
$upscope $end
$scope begin genblk1[7] $end
$var parameter 4 8 i $end
$upscope $end
$upscope $end
$scope begin $unm_blk_6 $end
$var integer 32 9 file [31:0] $end
$upscope $end
$upscope $end
$enddefinitions $end
$comment Show the parameter values. $end
$dumpall
b111 8
b110 7
b101 6
b100 5
b11 4
b10 3
b1 2
b0 1
b100000 0
b10000 /
b1000 .
b1111101000 &
b100000 %
b10000 $
b1000 #
b1100100 "
$end
#0
$dumpvars
b10 9
bx -
bx ,
b0 +
b0 *
0)
bx (
0'
bx !
$end
#50000
1'
#100000
0'
#150000
1'
#200000
0'
#250000
1'
#300000
0'
#350000
1'
#400000
0'
#450000
1'
#500000
0'
#550000
1'
#600000
0'
#650000
1'
#700000
0'
#750000
1'
#800000
0'
#850000
1'
#900000
0'
#950000
1'
#1000000
0'
#1050000
1'
#1100000
0'
#1150000
1'
#1200000
0'
#1250000
1'
#1300000
0'
#1350000
1'
#1400000
0'
#1450000
1'
#1500000
0'
#1550000
1'
#1600000
0'
#1650000
1'
#1700000
0'
#1750000
1'
#1800000
0'
#1850000
1'
#1900000
0'
#1950000
1'
#2000000
0'
1)
#2050000
b1 *
b11111111111111111111101110100000 !
b11111111111111111111101110100000 -
b1111111111011101 (
b1111111111011101 ,
1'
#2100000
0'
#2150000
b10 *
b11111111111111111111101010110000 !
b11111111111111111111101010110000 -
b1111111111110001 (
b1111111111110001 ,
1'
#2200000
0'
#2250000
b11 *
b11011000000 !
b11011000000 -
b1011001 (
b1011001 ,
1'
#2300000
0'
#2350000
b100 *
b11011110000 !
b11011110000 -
b11 (
b11 ,
1'
#2400000
0'
#2450000
b101 *
b100000 !
b100000 -
b1111111111001011 (
b1111111111001011 ,
1'
#2500000
0'
#2550000
b110 *
b11111111111111111111111010110000 !
b11111111111111111111111010110000 -
b1111111111101001 (
b1111111111101001 ,
1'
#2600000
0'
#2650000
b111 *
b101001000000 !
b101001000000 -
b1010001 (
b1010001 ,
1'
#2700000
0'
#2750000
b1000 *
b1000000000000 !
b1000000000000 -
b111001 (
b111001 ,
1'
#2800000
0'
#2850000
b1001 *
b1011010100000 !
b1011010100000 -
b1000000 (
b1000000 ,
1'
#2900000
0'
#2950000
b1010 *
b1000010110000 !
b1000010110000 -
b1111111111111010 (
b1111111111111010 ,
1'
#3000000
0'
#3050000
b1011 *
b1000001100000 !
b1000001100000 -
b100111 (
b100111 ,
1'
#3100000
0'
#3150000
b1100 *
b1011011010000 !
b1011011010000 -
b110010 (
b110010 ,
1'
#3200000
0'
#3250000
b1101 *
b1100110000000 !
b1100110000000 -
b10100 (
b10100 ,
1'
#3300000
0'
#3350000
b1110 *
b1011011000000 !
b1011011000000 -
b100101 (
b100101 ,
1'
#3400000
0'
#3450000
b1111 *
b1011000100000 !
b1011000100000 -
b110110 (
b110110 ,
1'
#3500000
0'
#3550000
b10000 *
b1011010100000 !
b1011010100000 -
b1001000 (
b1001000 ,
1'
#3600000
0'
#3650000
b10001 *
b101111100000 !
b101111100000 -
b1111111111101110 (
b1111111111101110 ,
1'
#3700000
0'
#3750000
b10010 *
b110110110000 !
b110110110000 -
b1000100 (
b1000100 ,
1'
#3800000
0'
#3850000
b10011 *
b110000100000 !
b110000100000 -
b101001 (
b101001 ,
1'
#3900000
0'
#3950000
b10100 *
b1000001110000 !
b1000001110000 -
b1011001 (
b1011001 ,
1'
#4000000
0'
#4050000
b10101 *
b110001100000 !
b110001100000 -
b10110 (
b10110 ,
1'
#4100000
0'
#4150000
b10110 *
b110100110000 !
b110100110000 -
b1000011 (
b1000011 ,
1'
#4200000
0'
#4250000
b10111 *
b1001001000000 !
b1001001000000 -
b1100101 (
b1100101 ,
1'
#4300000
0'
#4350000
b11000 *
b1001011010000 !
b1001011010000 -
b1111111111110111 (
b1111111111110111 ,
1'
#4400000
0'
#4450000
b11001 *
b10000010100000 !
b10000010100000 -
b1100001 (
b1100001 ,
1'
#4500000
0'
#4550000
b11010 *
b10001001010000 !
b10001001010000 -
b1000100 (
b1000100 ,
1'
#4600000
0'
#4650000
b11011 *
b10010111000000 !
b10010111000000 -
b1010010 (
b1010010 ,
1'
#4700000
0'
#4750000
b11100 *
b10101110000000 !
b10101110000000 -
b1110010 (
b1110010 ,
1'
#4800000
0'
#4850000
b11101 *
b10110101000000 !
b10110101000000 -
b1010010 (
b1010010 ,
1'
#4900000
0'
#4950000
b11110 *
b10111000110000 !
b10111000110000 -
b1110100 (
b1110100 ,
1'
#5000000
0'
#5050000
b11111 *
b11000000100000 !
b11000000100000 -
b1111100 (
b1111100 ,
1'
#5100000
0'
#5150000
b100000 *
b10110101010000 !
b10110101010000 -
b110100 (
b110100 ,
1'
#5200000
0'
#5250000
b100001 *
b11001011100000 !
b11001011100000 -
b1110111 (
b1110111 ,
1'
#5300000
0'
#5350000
b100010 *
b11001100010000 !
b11001100010000 -
b1010101 (
b1010101 ,
1'
#5400000
0'
#5450000
b100011 *
b11010110000000 !
b11010110000000 -
b1100111 (
b1100111 ,
1'
#5500000
0'
#5550000
b100100 *
b11100110110000 !
b11100110110000 -
b10010101 (
b10010101 ,
1'
#5600000
0'
#5650000
b100101 *
b11011110000000 !
b11011110000000 -
b1100010 (
b1100010 ,
1'
#5700000
0'
#5750000
b100110 *
b11011011100000 !
b11011011100000 -
b1110010 (
b1110010 ,
1'
#5800000
0'
#5850000
b100111 *
b11001111000000 !
b11001111000000 -
b1011110 (
b1011110 ,
1'
#5900000
0'
#5950000
b101000 *
b10110111100000 !
b10110111100000 -
b11001 (
b11001 ,
1'
#6000000
0'
#6050000
b101001 *
b11000101100000 !
b11000101100000 -
b1100100 (
b1100100 ,
1'
#6100000
0'
#6150000
b101010 *
b10111101110000 !
b10111101110000 -
b1001000 (
b1001000 ,
1'
#6200000
0'
#6250000
b101011 *
b11100100100000 !
b11100100100000 -
b10100101 (
b10100101 ,
1'
#6300000
0'
#6350000
b101100 *
b11111001110000 !
b11111001110000 -
b10110111 (
b10110111 ,
1'
#6400000
0'
#6450000
b101101 *
b11010110100000 !
b11010110100000 -
b1000110 (
b1000110 ,
1'
#6500000
0'
#6550000
b101110 *
b11100010000000 !
b11100010000000 -
b10001100 (
b10001100 ,
1'
#6600000
0'
#6650000
b101111 *
b11010101000000 !
b11010101000000 -
b1011011 (
b1011011 ,
1'
#6700000
0'
#6750000
b110000 *
b11001111100000 !
b11001111100000 -
b1001110 (
b1001110 ,
1'
#6800000
0'
#6850000
b110001 *
b100000001100000 !
b100000001100000 -
b10111101 (
b10111101 ,
1'
#6900000
0'
#6950000
b110010 *
b11100111100000 !
b11100111100000 -
b111101 (
b111101 ,
1'
#7000000
0'
#7050000
b110011 *
b11011111100000 !
b11011111100000 -
b1100001 (
b1100001 ,
1'
#7100000
0'
#7150000
b110100 *
b11110101000000 !
b11110101000000 -
b10011100 (
b10011100 ,
1'
#7200000
0'
#7250000
b110101 *
b100100000100000 !
b100100000100000 -
b11001000 (
b11001000 ,
1'
#7300000
0'
#7350000
b110110 *
b100011011000000 !
b100011011000000 -
b1000101 (
b1000101 ,
1'
#7400000
0'
#7450000
b110111 *
b100101011000000 !
b100101011000000 -
b1110000 (
b1110000 ,
1'
#7500000
0'
#7550000
b111000 *
b100010010100000 !
b100010010100000 -
b1011011 (
b1011011 ,
1'
#7600000
0'
#7650000
b111001 *
b100010110000000 !
b100010110000000 -
b10010011 (
b10010011 ,
1'
#7700000
0'
#7750000
b111010 *
b100100010110000 !
b100100010110000 -
b10010100 (
b10010100 ,
1'
#7800000
0'
#7850000
b111011 *
b100101010000000 !
b100101010000000 -
b10001001 (
b10001001 ,
1'
#7900000
0'
#7950000
b111100 *
b100010001110000 !
b100010001110000 -
b1100111 (
b1100111 ,
1'
#8000000
0'
#8050000
b111101 *
b100001011100000 !
b100001011100000 -
b10001011 (
b10001011 ,
1'
#8100000
0'
#8150000
b111110 *
b100011111100000 !
b100011111100000 -
b11000000 (
b11000000 ,
1'
#8200000
0'
#8250000
b111111 *
b100011001000000 !
b100011001000000 -
b10001011 (
b10001011 ,
1'
#8300000
0'
#8350000
b1000000 *
b100010111100000 !
b100010111100000 -
b10001101 (
b10001101 ,
1'
#8400000
0'
#8450000
b1000001 *
b11111111100000 !
b11111111100000 -
b1100000 (
b1100000 ,
1'
#8500000
0'
#8550000
b1000010 *
b11111101100000 !
b11111101100000 -
b10000001 (
b10000001 ,
1'
#8600000
0'
#8650000
b1000011 *
b100010110000000 !
b100010110000000 -
b10110110 (
b10110110 ,
1'
#8700000
0'
#8750000
b1000100 *
b100011000000000 !
b100011000000000 -
b10010011 (
b10010011 ,
1'
#8800000
0'
#8850000
b1000101 *
b100001011000000 !
b100001011000000 -
b1110101 (
b1110101 ,
1'
#8900000
0'
#8950000
b1000110 *
b100000011100000 !
b100000011100000 -
b1101101 (
b1101101 ,
1'
#9000000
0'
#9050000
b1000111 *
b100000110000000 !
b100000110000000 -
b10000001 (
b10000001 ,
1'
#9100000
0'
#9150000
b1001000 *
b100001111010000 !
b100001111010000 -
b10000101 (
b10000101 ,
1'
#9200000
0'
#9250000
b1001001 *
b11110000000000 !
b11110000000000 -
b110100 (
b110100 ,
1'
#9300000
0'
#9350000
b1001010 *
b11101000010000 !
b11101000010000 -
b10010111 (
b10010111 ,
1'
#9400000
0'
#9450000
b1001011 *
b11001101100000 !
b11001101100000 -
b1110001 (
b1110001 ,
1'
#9500000
0'
#9550000
b1001100 *
b11000110010000 !
b11000110010000 -
b1011000 (
b1011000 ,
1'
#9600000
0'
#9650000
b1001101 *
b10100110100000 !
b10100110100000 -
b100111 (
b100111 ,
1'
#9700000
0'
#9750000
b1001110 *
b10011001000000 !
b10011001000000 -
b1001011 (
b1001011 ,
1'
#9800000
0'
#9850000
b1001111 *
b10110001100000 !
b10110001100000 -
b10010111 (
b10010111 ,
1'
#9900000
0'
#9950000
b1010000 *
b10111101110000 !
b10111101110000 -
b1100101 (
b1100101 ,
1'
#10000000
0'
#10050000
b1010001 *
b11001000100000 !
b11001000100000 -
b1100010 (
b1100010 ,
1'
#10100000
0'
#10150000
b1010010 *
b11001110100000 !
b11001110100000 -
b10001001 (
b10001001 ,
1'
#10200000
0'
#10250000
b1010011 *
b11100111100000 !
b11100111100000 -
b10101111 (
b10101111 ,
1'
#10300000
0'
#10350000
b1010100 *
b11110011110000 !
b11110011110000 -
b1011000 (
b1011000 ,
1'
#10400000
0'
#10450000
b1010101 *
b100010000000000 !
b100010000000000 -
b1111000 (
b1111000 ,
1'
#10500000
0'
#10550000
b1010110 *
b100000100010000 !
b100000100010000 -
b1101000 (
b1101000 ,
1'
#10600000
0'
#10650000
b1010111 *
b11110111000000 !
b11110111000000 -
b1100101 (
b1100101 ,
1'
#10700000
0'
#10750000
b1011000 *
b11110111100000 !
b11110111100000 -
b1100100 (
b1100100 ,
1'
#10800000
0'
#10850000
b11111000000000 !
b11111000000000 -
b1011001 *
1'
#10900000
0'
#10950000
b1011010 *
b11101010110000 !
b11101010110000 -
b1111010 (
b1111010 ,
1'
#11000000
0'
#11050000
b1011011 *
b11001001000000 !
b11001001000000 -
b1010001 (
b1010001 ,
1'
#11100000
0'
#11150000
b1011100 *
b11001011000000 !
b11001011000000 -
b10000000 (
b10000000 ,
1'
#11200000
0'
#11250000
b1011101 *
b10111011100000 !
b10111011100000 -
b1011101 (
b1011101 ,
1'
#11300000
0'
#11350000
b1011110 *
b10110001100000 !
b10110001100000 -
b111101 (
b111101 ,
1'
#11400000
0'
#11450000
b1011111 *
b11101110000000 !
b11101110000000 -
b11001010 (
b11001010 ,
1'
#11500000
0'
#11550000
b1100000 *
b11100110110000 !
b11100110110000 -
b1000111 (
b1000111 ,
1'
#11600000
0'
#11650000
b1100001 *
b11100111000000 !
b11100111000000 -
b1010110 (
b1010110 ,
1'
#11700000
0'
#11750000
b1100010 *
b11101111110000 !
b11101111110000 -
b1110100 (
b1110100 ,
1'
#11800000
0'
#11850000
b1100011 *
b11010110100000 !
b11010110100000 -
b110000 (
b110000 ,
1'
#11900000
0'
#11950000
b1100100 *
b10111110010000 !
b10111110010000 -
b1111111111111100 (
b1111111111111100 ,
1'
#12000000
0'
#12050000
b1100101 *
b10111001100000 !
b10111001100000 -
b100011 (
b100011 ,
1'
#12100000
0'
#12150000
b1100110 *
b10010011010000 !
b10010011010000 -
b110001 (
b110001 ,
1'
#12200000
0'
#12250000
b1100111 *
b10000011000000 !
b10000011000000 -
b1011101 (
b1011101 ,
1'
#12300000
0'
#12350000
b1101000 *
b10001100010000 !
b10001100010000 -
b1111011 (
b1111011 ,
1'
#12400000
0'
#12450000
b1101001 *
b1110001000000 !
b1110001000000 -
b110010 (
b110010 ,
1'
#12500000
0'
#12550000
b1101010 *
b1101100100000 !
b1101100100000 -
b11110 (
b11110 ,
1'
#12600000
0'
#12650000
b1101011 *
b10000001100000 !
b10000001100000 -
b1010001 (
b1010001 ,
1'
#12700000
0'
#12750000
b1101100 *
b1111011100000 !
b1111011100000 -
b1011 (
b1011 ,
1'
#12800000
0'
#12850000
b1101101 *
b10011000000000 !
b10011000000000 -
b1010000 (
b1010000 ,
1'
#12900000
0'
#12950000
b1101110 *
b10000000010000 !
b10000000010000 -
b1111111111111110 (
b1111111111111110 ,
1'
#13000000
0'
#13050000
b1101111 *
b10010101100000 !
b10010101100000 -
b1011000 (
b1011000 ,
1'
#13100000
0'
#13150000
b1110000 *
b10100001010000 !
b10100001010000 -
b1100001 (
b1100001 ,
1'
#13200000
0'
#13250000
b1110001 *
b10010100100000 !
b10010100100000 -
b110000 (
b110000 ,
1'
#13300000
0'
#13350000
b1110010 *
b10011100100000 !
b10011100100000 -
b1110001 (
b1110001 ,
1'
#13400000
0'
#13450000
b1110011 *
b10001011000000 !
b10001011000000 -
b111110 (
b111110 ,
1'
#13500000
0'
#13550000
b1110100 *
b1110000110000 !
b1110000110000 -
b1111111111100111 (
b1111111111100111 ,
1'
#13600000
0'
#13650000
b1110101 *
b10000110000000 !
b10000110000000 -
b1000110 (
b1000110 ,
1'
#13700000
0'
#13750000
b1110110 *
b1110010100000 !
b1110010100000 -
b1010 (
b1010 ,
1'
#13800000
0'
#13850000
b1110111 *
b1010001100000 !
b1010001100000 -
b1111111111101111 (
b1111111111101111 ,
1'
#13900000
0'
#13950000
b1111000 *
b1010101100000 !
b1010101100000 -
b1000000 (
b1000000 ,
1'
#14000000
0'
#14050000
b1111001 *
b1010010100000 !
b1010010100000 -
b110010 (
b110010 ,
1'
#14100000
0'
#14150000
b1111010 *
b1000000010000 !
b1000000010000 -
b1111111111110101 (
b1111111111110101 ,
1'
#14200000
0'
#14250000
b1111011 *
b101001000000 !
b101001000000 -
b1111111111101011 (
b1111111111101011 ,
1'
#14300000
0'
#14350000
b1111100 *
b1010010000 !
b1010010000 -
b1111111111001011 (
b1111111111001011 ,
1'
#14400000
0'
#14450000
b1111101 *
b11111111111111111111111011100000 !
b11111111111111111111111011100000 -
b1111111111101011 (
b1111111111101011 ,
1'
#14500000
0'
#14550000
b1111110 *
b1001010000 !
b1001010000 -
b100110 (
b100110 ,
1'
#14600000
0'
#14650000
b1111111 *
b11111111111111111111111101100000 !
b11111111111111111111111101100000 -
b1111111111110011 (
b1111111111110011 ,
1'
#14700000
0'
#14750000
b10000000 *
b11111111111111111111110110100000 !
b11111111111111111111110110100000 -
b10110 (
b10110 ,
1'
#14800000
0'
#14850000
b10000001 *
b11111111111111111111001011000000 !
b11111111111111111111001011000000 -
b1111111111001101 (
b1111111111001101 ,
1'
#14900000
0'
#14950000
b10000010 *
b11111111111111111111001001010000 !
b11111111111111111111001001010000 -
b1111111111100100 (
b1111111111100100 ,
1'
#15000000
0'
#15050000
b10000011 *
b11111111111111111110111101100000 !
b11111111111111111110111101100000 -
b1111111111010000 (
b1111111111010000 ,
1'
#15100000
0'
#15150000
b10000100 *
b11111111111111111110110110000000 !
b11111111111111111110110110000000 -
b1111111111001101 (
b1111111111001101 ,
1'
#15200000
0'
#15250000
b10000101 *
b11111111111111111111001101100000 !
b11111111111111111111001101100000 -
b1011 (
b1011 ,
1'
#15300000
0'
#15350000
b10000110 *
b11111111111111111111001100010000 !
b11111111111111111111001100010000 -
b1111111111101110 (
b1111111111101110 ,
1'
#15400000
0'
#15450000
b10000111 *
b11111111111111111110111011100000 !
b11111111111111111110111011100000 -
b1111111111001111 (
b1111111111001111 ,
1'
#15500000
0'
#15550000
b10001000 *
b11111111111111111111000000000000 !
b11111111111111111111000000000000 -
b1111111111011111 (
b1111111111011111 ,
1'
#15600000
0'
#15650000
b10001001 *
b11111111111111111111000001000000 !
b11111111111111111111000001000000 -
b1111111111011000 (
b1111111111011000 ,
1'
#15700000
0'
#15750000
b10001010 *
b11111111111111111111000011110000 !
b11111111111111111111000011110000 -
b1111111111011011 (
b1111111111011011 ,
1'
#15800000
0'
#15850000
b10001011 *
b11111111111111111111010010100000 !
b11111111111111111111010010100000 -
b1111111111110011 (
b1111111111110011 ,
1'
#15900000
0'
#15950000
b10001100 *
b11111111111111111111001100110000 !
b11111111111111111111001100110000 -
b1111111111110100 (
b1111111111110100 ,
1'
#16000000
0'
#16050000
b10001101 *
b11111111111111111110111001100000 !
b11111111111111111110111001100000 -
b1111111111011001 (
b1111111111011001 ,
1'
#16100000
0'
#16150000
b10001110 *
b11111111111111111110111000110000 !
b11111111111111111110111000110000 -
b1111111111001100 (
b1111111111001100 ,
1'
#16200000
0'
#16250000
b10001111 *
b11111111111111111110101011100000 !
b11111111111111111110101011100000 -
b1111111110110011 (
b1111111110110011 ,
1'
#16300000
0'
#16350000
b10010000 *
b11111111111111111110101011010000 !
b11111111111111111110101011010000 -
b1111111111010111 (
b1111111111010111 ,
1'
#16400000
0'
#16450000
b10010001 *
b11111111111111111110100110100000 !
b11111111111111111110100110100000 -
b1111111111001110 (
b1111111111001110 ,
1'
#16500000
0'
#16550000
b10010010 *
b11111111111111111110101011000000 !
b11111111111111111110101011000000 -
b101 (
b101 ,
1'
#16600000
0'
#16650000
b10010011 *
b11111111111111111110110101000000 !
b11111111111111111110110101000000 -
b10000 (
b10000 ,
1'
#16700000
0'
#16750000
b10010100 *
b11111111111111111110111101110000 !
b11111111111111111110111101110000 -
b1111111111111100 (
b1111111111111100 ,
1'
#16800000
0'
#16850000
b10010101 *
b11111111111111111110100011100000 !
b11111111111111111110100011100000 -
b1111111110110110 (
b1111111110110110 ,
1'
#16900000
0'
#16950000
b10010110 *
b11111111111111111110100011000000 !
b11111111111111111110100011000000 -
b1111111110110001 (
b1111111110110001 ,
1'
#17000000
0'
#17050000
b10010111 *
b11111111111111111110101011000000 !
b11111111111111111110101011000000 -
b1111111111000010 (
b1111111111000010 ,
1'
#17100000
0'
#17150000
b10011000 *
b11111111111111111110101000110000 !
b11111111111111111110101000110000 -
b1111111111000101 (
b1111111111000101 ,
1'
#17200000
0'
#17250000
b10011001 *
b11111111111111111110111100100000 !
b11111111111111111110111100100000 -
b1111111111110001 (
b1111111111110001 ,
1'
#17300000
0'
#17350000
b10011010 *
b11111111111111111110110000000000 !
b11111111111111111110110000000000 -
b1111111111011110 (
b1111111111011110 ,
1'
#17400000
0'
#17450000
b10011011 *
b11111111111111111110010001000000 !
b11111111111111111110010001000000 -
b1111111110111001 (
b1111111110111001 ,
1'
#17500000
0'
#17550000
b10011100 *
b11111111111111111110010111110000 !
b11111111111111111110010111110000 -
b1111111111010001 (
b1111111111010001 ,
1'
#17600000
0'
#17650000
b10011101 *
b11111111111111111110011111100000 !
b11111111111111111110011111100000 -
b1111111111010011 (
b1111111111010011 ,
1'
#17700000
0'
#17750000
b10011110 *
b11111111111111111110010010110000 !
b11111111111111111110010010110000 -
b1111111110001111 (
b1111111110001111 ,
1'
#17800000
0'
#17850000
b10011111 *
b11111111111111111110010011000000 !
b11111111111111111110010011000000 -
b1111111110101001 (
b1111111110101001 ,
1'
#17900000
0'
#17950000
b10100000 *
b11111111111111111110001001010000 !
b11111111111111111110001001010000 -
b1111111111001010 (
b1111111111001010 ,
1'
#18000000
0'
#18050000
b10100001 *
b11111111111111111101001011000000 !
b11111111111111111101001011000000 -
b1111111101100001 (
b1111111101100001 ,
1'
#18100000
0'
#18150000
b10100010 *
b11111111111111111100111100000000 !
b11111111111111111100111100000000 -
b1111111101111101 (
b1111111101111101 ,
1'
#18200000
0'
#18250000
b10100011 *
b11111111111111111101001110100000 !
b11111111111111111101001110100000 -
b1111111111000000 (
b1111111111000000 ,
1'
#18300000
0'
#18350000
b10100100 *
b11111111111111111100111011100000 !
b11111111111111111100111011100000 -
b1111111110000111 (
b1111111110000111 ,
1'
#18400000
0'
#18450000
b10100101 *
b11111111111111111100011011000000 !
b11111111111111111100011011000000 -
b1111111101101100 (
b1111111101101100 ,
1'
#18500000
0'
#18550000
b10100110 *
b11111111111111111100010111110000 !
b11111111111111111100010111110000 -
b1111111110011100 (
b1111111110011100 ,
1'
#18600000
0'
#18650000
b10100111 *
b11111111111111111100100100000000 !
b11111111111111111100100100000000 -
b1111111110111011 (
b1111111110111011 ,
1'
#18700000
0'
#18750000
b10101000 *
b11111111111111111100110101110000 !
b11111111111111111100110101110000 -
b1111111110101000 (
b1111111110101000 ,
1'
#18800000
0'
#18850000
b10101001 *
b11111111111111111100101100000000 !
b11111111111111111100101100000000 -
b1111111101110001 (
b1111111101110001 ,
1'
#18900000
0'
#18950000
b10101010 *
b11111111111111111100010010100000 !
b11111111111111111100010010100000 -
b1111111101011010 (
b1111111101011010 ,
1'
#19000000
0'
#19050000
b10101011 *
b11111111111111111100101011000000 !
b11111111111111111100101011000000 -
b1111111110111110 (
b1111111110111110 ,
1'
#19100000
0'
#19150000
b10101100 *
b11111111111111111100101101000000 !
b11111111111111111100101101000000 -
b1111111101110100 (
b1111111101110100 ,
1'
#19200000
0'
#19250000
b10101101 *
b11111111111111111100111000000000 !
b11111111111111111100111000000000 -
b1111111110000110 (
b1111111110000110 ,
1'
#19300000
0'
#19350000
b10101110 *
b11111111111111111100110000010000 !
b11111111111111111100110000010000 -
b1111111110011100 (
b1111111110011100 ,
1'
#19400000
0'
#19450000
b10101111 *
b11111111111111111100101010000000 !
b11111111111111111100101010000000 -
b1111111110011111 (
b1111111110011111 ,
1'
#19500000
0'
#19550000
b10110000 *
b11111111111111111100110100100000 !
b11111111111111111100110100100000 -
b1111111110011011 (
b1111111110011011 ,
1'
#19600000
0'
#19650000
b10110001 *
b11111111111111111101000011100000 !
b11111111111111111101000011100000 -
b1111111110100100 (
b1111111110100100 ,
1'
#19700000
0'
#19750000
b10110010 *
b11111111111111111100100101100000 !
b11111111111111111100100101100000 -
b1111111101000110 (
b1111111101000110 ,
1'
#19800000
0'
#19850000
b10110011 *
b11111111111111111100110100100000 !
b11111111111111111100110100100000 -
b1111111110100000 (
b1111111110100000 ,
1'
#19900000
0'
#19950000
b10110100 *
b11111111111111111100101110010000 !
b11111111111111111100101110010000 -
b1111111101101101 (
b1111111101101101 ,
1'
#20000000
0'
#20050000
b10110101 *
b11111111111111111100110011100000 !
b11111111111111111100110011100000 -
b1111111110000100 (
b1111111110000100 ,
1'
#20100000
0'
#20150000
b10110110 *
b11111111111111111100100110100000 !
b11111111111111111100100110100000 -
b1111111101101011 (
b1111111101101011 ,
1'
#20200000
0'
#20250000
b10110111 *
b11111111111111111100100010100000 !
b11111111111111111100100010100000 -
b1111111101111101 (
b1111111101111101 ,
1'
#20300000
0'
#20350000
b10111000 *
b11111111111111111100100010100000 !
b11111111111111111100100010100000 -
b1111111110100100 (
b1111111110100100 ,
1'
#20400000
0'
#20450000
b10111001 *
b11111111111111111100001100000000 !
b11111111111111111100001100000000 -
b1111111101110111 (
b1111111101110111 ,
1'
#20500000
0'
#20550000
b10111010 *
b11111111111111111100001001110000 !
b11111111111111111100001001110000 -
b1111111110010111 (
b1111111110010111 ,
1'
#20600000
0'
#20650000
b10111011 *
b11111111111111111100000001100000 !
b11111111111111111100000001100000 -
b1111111110001011 (
b1111111110001011 ,
1'
#20700000
0'
#20750000
b10111100 *
b11111111111111111100000100110000 !
b11111111111111111100000100110000 -
b1111111110010001 (
b1111111110010001 ,
1'
#20800000
0'
#20850000
b10111101 *
b11111111111111111011110001000000 !
b11111111111111111011110001000000 -
b1111111101100011 (
b1111111101100011 ,
1'
#20900000
0'
#20950000
b10111110 *
b11111111111111111011110100010000 !
b11111111111111111011110100010000 -
b1111111110001010 (
b1111111110001010 ,
1'
#21000000
0'
#21050000
b10111111 *
b11111111111111111100000100000000 !
b11111111111111111100000100000000 -
b1111111110100011 (
b1111111110100011 ,
1'
#21100000
0'
#21150000
b11000000 *
b11111111111111111100000101100000 !
b11111111111111111100000101100000 -
b1111111101111101 (
b1111111101111101 ,
1'
#21200000
0'
#21250000
b11000001 *
b11111111111111111100001010000000 !
b11111111111111111100001010000000 -
b1111111110000011 (
b1111111110000011 ,
1'
#21300000
0'
#21350000
b11000010 *
b11111111111111111100011011000000 !
b11111111111111111100011011000000 -
b1111111111001111 (
b1111111111001111 ,
1'
#21400000
0'
#21450000
b11000011 *
b11111111111111111011111110100000 !
b11111111111111111011111110100000 -
b1111111101110100 (
b1111111101110100 ,
1'
#21500000
0'
#21550000
b11000100 *
b11111111111111111011111010100000 !
b11111111111111111011111010100000 -
b1111111101010011 (
b1111111101010011 ,
1'
#21600000
0'
#21650000
b11000101 *
b11111111111111111100010000100000 !
b11111111111111111100010000100000 -
b1111111110000111 (
b1111111110000111 ,
1'
#21700000
0'
#21750000
b11000110 *
b11111111111111111100000000100000 !
b11111111111111111100000000100000 -
b1111111101100011 (
b1111111101100011 ,
1'
#21800000
0'
#21850000
b11000111 *
b11111111111111111100001100000000 !
b11111111111111111100001100000000 -
b1111111110011010 (
b1111111110011010 ,
1'
#21900000
0'
