fifo/Fifo.sv
`default_nettype none
`timescale 1ns/1ps

module Fifo #(
    parameter LEN = 10,
    parameter SIZE = 32
) (
    input logic clk_i,
    input logic rst_i,
    input logic valid_i,
    input logic ready_i,
    input logic[SIZE-1:0] data_i,
    output logic[SIZE-1:0] data_o,
    output logic valid_o,
    output logic is_full_o
);

localparam PTR_BIT = 32;


// VARIABLE INDEXING FOR STRUCT TYPE ARRAY NOT SUPPORTED BY ICARUS (╥﹏╥)

// typedef struct packed {
//     bit data_valid;
//     logic[SIZE-1:0] data;
// } fifo_entry;

/////////////////////////////////////////////////////////////////////////////////////////
// fifo_entry [LEN-1:0] fifo;

logic [PTR_BIT-1:0] w_ptr, r_ptr;
logic [SIZE-1:0] fifo [LEN-1:0];
logic [LEN-1:0] data_stored;

assign is_full_o = & (data_stored);

always_ff @( posedge clk_i ) begin
    if (rst_i == 1'b0) begin
        w_ptr <= '0;
        r_ptr <= '0;
        // fifo <= '0;
        data_stored <= '0;
        data_o <= '0;
        valid_o <= 1'b0;
    end else begin
        valid_o <= 1'b0;
        if (valid_i == 1'b1) begin // data to be written
            w_ptr <= (w_ptr < LEN-1) ? w_ptr + 'd1 : '0;
            fifo[w_ptr] <= data_i;
            data_stored[w_ptr] <= 1'b1;
        end else if (ready_i == 1'b1) begin // data to be read
            r_ptr <= (r_ptr < LEN-1) ? r_ptr + 'd1 : '0;
            data_o <= fifo[r_ptr];
            data_stored <= 1'b0;
            valid_o <= 1'b1;
        end else begin
            r_ptr <= r_ptr;
            w_ptr <= w_ptr;
            // fifo <= fifo;
        end
    end
end


/////////////////////////////////////////////////////////////////////////////////////////
// ASSERTIONS --- NOT SUPPORTED BY ICARUS (╥﹏╥)
// property correct_read @(posedge clk_i); // when reading, r_ptr should store a valid data value.
//     ready_i |-> fifo[r_ptr].data_valid;
// endproperty
// assert property (correct_read) 
// else  $fatal("Incorrect READ");

// property correct_write @(posedge clk_i); // when writing, w_ptr should be empty.
//     valid_i |-> ! fifo[w_ptr].data_valid;
// endproperty
// assert property (correct_write) 
// else  $fatal("Incorrect WRITE");

// property overflow @(posedge clk_i); 
//     is_full_o |-> ! valid_i;
// endproperty
// assert property (overflow) 
// else  $fatal("OVERFLOW");

endmodule

fifo/fifo_tb.sv
`default_nettype none
`timescale 1ns/1ps


module fifo_tb();

localparam CLOCKPERIOD = 100;
localparam SIZE = 32;
localparam LEN = 50;

logic clk_i, rst_i, valid_in, ready_in, valid_out, is_full_out;
logic [SIZE-1:0] data_write, data_read;

initial clk_i = 1'b0;
initial rst_i = 1'b0;

always #(CLOCKPERIOD/2) clk_i = ~clk_i;

initial begin
    #(20*CLOCKPERIOD+3);
    rst_i = 1'b1;
end


initial begin
    valid_in = 1'b0;
    ready_in = 1'b0;
    data_write = 'd0;

    wait (rst_i);
        #(CLOCKPERIOD);
        valid_in = 1'b1;
        data_write = 32'habcdefaa;
        #(CLOCKPERIOD);
        data_write = 32'hdeaddead;
        #(CLOCKPERIOD);
        data_write = 32'haaaaaaaa;
        #(CLOCKPERIOD);
        data_write = 32'hdddddddd;
        #(CLOCKPERIOD);
        valid_in = 1'b0;
        #(CLOCKPERIOD);
        ready_in = 1'b1;
        #(2*CLOCKPERIOD);
        ready_in = 1'b0;
end

Fifo #(
    .SIZE(SIZE),
    .LEN(LEN)
) fifo_uut (
    .clk_i,
    .rst_i,
    .valid_i(valid_in),
    .ready_i(ready_in),
    .data_i(data_write),
    .data_o(data_read),
    .valid_o(valid_out),
    .is_full_o(is_full_out)
);

initial begin
    $dumpfile("fifo.vcd");
    $dumpvars(0, fifo_tb);
    
    #(500*CLOCKPERIOD);
    $finish(0);
end




endmodule

fifo/fifo.vcd
$date
	Mon Jan 26 20:37:13 2026
$end
$version
	Icarus Verilog
$end
$timescale
	1ps
$end
$scope module fifo_tb $end
$var wire 1 ! valid_out $end
$var wire 1 " is_full_out $end
$var wire 32 # data_read [31:0] $end
$var parameter 32 $ CLOCKPERIOD $end
$var parameter 32 % LEN $end
$var parameter 32 & SIZE $end
$var reg 1 ' clk_i $end
$var reg 32 ( data_write [31:0] $end
$var reg 1 ) ready_in $end
$var reg 1 * rst_i $end
$var reg 1 + valid_in $end
$scope module fifo_uut $end
$var wire 1 ' clk_i $end
$var wire 32 , data_i [31:0] $end
$var wire 1 ) ready_i $end
$var wire 1 * rst_i $end
$var wire 1 + valid_i $end
$var wire 1 " is_full_o $end
$var parameter 32 - LEN $end
$var parameter 32 . PTR_BIT $end
$var parameter 32 / SIZE $end
$var reg 32 0 data_o [31:0] $end
$var reg 50 1 data_stored [49:0] $end
$var reg 32 2 r_ptr [31:0] $end
$var reg 1 ! valid_o $end
$var reg 32 3 w_ptr [31:0] $end
$upscope $end
$upscope $end
$enddefinitions $end
$comment Show the parameter values. $end
$dumpall
b100000 /
b100000 .
b110010 -
b100000 &
b110010 %
b1100100 $
$end
#0
$dumpvars
bx 3
bx 2
bx 1
bx 0
b0 ,
0+
0*
0)
b0 (
0'
bx #
x"
x!
$end
#50000
0!
b0 #
b0 0
0"
b0 1
b0 2
b0 3
1'
#100000
0'
#150000
1'
#200000
0'
#250000
1'
#300000
0'
#350000
1'
#400000
0'
#450000
1'
#500000
0'
#550000
1'
#600000
0'
#650000
1'
#700000
0'
#750000
1'
#800000
0'
#850000
1'
#900000
0'
#950000
1'
#1000000
0'
#1050000
1'
#1100000
0'
#1150000
1'
#1200000
0'
#1250000
1'
#1300000
0'
#1350000
1'
#1400000
0'
#1450000
1'
#1500000
0'
#1550000
1'
#1600000
0'
#1650000
1'
#1700000
0'
#1750000
1'
#1800000
0'
#1850000
1'
#1900000
0'
#1950000
1'
#2000000
0'
#2003000
1*
#2050000
1'
#2100000
0'
#2103000
b10101011110011011110111110101010 (
b10101011110011011110111110101010 ,
1+
#2150000
b1 1
b1 3
1'
#2200000
0'
#2203000
b11011110101011011101111010101101 (
b11011110101011011101111010101101 ,
#2250000
b11 1
b10 3
1'
#2300000
0'
#2303000
b10101010101010101010101010101010 (
b10101010101010101010101010101010 ,
#2350000
b111 1
b11 3
1'
#2400000
0'
#2403000
b11011101110111011101110111011101 (
b11011101110111011101110111011101 ,
#2450000
b1111 1
b100 3
1'
#2500000
0'
#2503000
0+
#2550000
1'
#2600000
0'
#2603000
1)
#2650000
1!
b0 1
b10101011110011011110111110101010 #
b10101011110011011110111110101010 0
b1 2
1'
#2700000
0'
#2750000
b11011110101011011101111010101101 #
b11011110101011011101111010101101 0
b10 2
1!
1'
#2800000
0'
#2803000
0)
#2850000
0!
1'
