elevator_logic/ElevatorLogic.sv
module ElevatorLogic #(
    parameter MAXFLOORS = 10,
    parameter MINFLOORS = 0
) (
    input logic clk_i,
    input logic rst_i,
    input logic request_i,
    input logic[3:0] requested_current_floor_i,
    input logic[3:0] requested_destination_floor_i,
    output logic[3:0] floor_o,
    output logic[1:0] direction_o,
    output logic request_served_o
);


localparam GOING_UP = 2'b11;
localparam GOING_DOWN = 2'b00;
localparam STATIONARY = 2'b01;
localparam N_FLOORS = MAXFLOORS-MINFLOORS;

typedef enum bit[1:0] {state_stationary, state_up, state_down} state_t;
state_t current_state, next_state;
logic[3:0] current_floor;
logic [1:0] prev_direction_q0, prev_direction_q1;
logic[N_FLOORS-1:0] pressed_buttons;

always_ff @(posedge clk_i) begin 
    if (rst_i == 1'b0) begin
        current_floor <= '0;
        current_state <= state_stationary;
        next_state <= state_stationary;
        pressed_buttons <= '0;
        prev_direction_q0 <= '0;
        prev_direction_q1 <= '0;
    end else begin
        current_state <= next_state;
        if(current_floor == requested_current_floor_i && current_state == state_stationary) begin // button is pressed only when person enters the elevator.
            pressed_buttons[requested_destination_floor_i] <= 1'b1;
        end else if (pressed_buttons[current_floor+1] == 1'b1 && current_state == state_up ) begin // button is de-pressed once the person steps out of the elevator. Compensate for 1 clk delay
            pressed_buttons[current_floor+1] = 1'b0;
        end else if (pressed_buttons[current_floor-1] == 1'b1 && current_state == state_down) begin // button is de-pressed once the person steps out of the elevator. Compensate for 1 clk delay
            pressed_buttons[current_floor-1] = 1'b0;
        end else pressed_buttons <= pressed_buttons;

        prev_direction_q0 <= direction_o; // what direction the elevator was moving before stopping (retain for two clks)
        prev_direction_q1 <= prev_direction_q0; 

        // current_floor manipulations 
        if (current_state == state_stationary) current_floor <= current_floor;
        else if (current_state == state_up) current_floor <= current_floor + 1'd1;
        else  current_floor <= current_floor - 1'd1;
    end
end

always_comb begin : state_update
    case (current_state)
        state_stationary : begin
            if (| pressed_buttons == 1'b0 && request_i == 1'b0 ) begin // there are no pressed button and no requests made
                next_state = state_stationary;
            end else if (| pressed_buttons == 1'b0 && request_i == 1'b1 ) begin // there is new request
                if (requested_current_floor_i < current_floor) next_state = state_down;
                else if (requested_current_floor_i > current_floor) next_state = state_up;
                else next_state = state_stationary;                
            end else begin
                if (prev_direction_q1 == GOING_UP) next_state = state_up;
                else if (prev_direction_q1 == GOING_DOWN) next_state = state_down;
                else next_state = state_stationary;
            end
        end
        state_up : begin
            if (pressed_buttons[current_floor+1] == 1'b1 || requested_current_floor_i == current_floor+1) begin
                next_state = state_stationary;
            end else next_state = state_up;
        end
        state_down : begin
            if (pressed_buttons[current_floor-1] == 1'b1 || requested_current_floor_i == current_floor-1) begin
                next_state = state_stationary;
            end else next_state = state_down;
        end
        default: 
            next_state = state_stationary;
    endcase
    
end

always_comb begin : output_block
    case(current_state)
        state_stationary : begin
            direction_o = STATIONARY;
            request_served_o = (current_floor == requested_current_floor_i) ? 1'b1 : 1'b0;
            floor_o = current_floor;
        end
        state_up : begin
            direction_o = GOING_UP;
            request_served_o = 1'b0;
            floor_o = current_floor;
        end
        state_down : begin
            direction_o = GOING_DOWN;
            request_served_o = 1'b0;
            floor_o = current_floor;
        end
        default : begin
            direction_o = STATIONARY;
            request_served_o = 1'b1;
            floor_o = current_floor;
        end
    endcase
end



endmodule

elevator_logic/elevator_tb.sv
`timescale 1ns/1ps
`default_nettype none

module elevator_tb();

localparam CLOCKPERIOD = 100;
localparam MAXFLOORS = 10;
localparam MINFLOORS = 0;

logic clk_i,rst_i;
logic[3:0] current_floor, destination_floor, elevator_current_floor;
logic[1:0] elevator_direction;
logic ready, request;

initial clk_i = 1'b0;
initial rst_i = 1'b0;

always #(CLOCKPERIOD/2) clk_i = ~clk_i;

initial begin
    #(20*CLOCKPERIOD + 3);
    rst_i = 1'b1;
end

initial begin
    wait(rst_i);
        #(2*CLOCKPERIOD);
        request = 1'b1;
        current_floor = 4'd4;
        destination_floor = 4'd8;
        wait(ready) request = 1'b0;
end

ElevatorLogic #(
    .MAXFLOORS(MAXFLOORS),
    .MINFLOORS(MINFLOORS)
) elevator_uut (
    .clk_i,
    .rst_i,
    .request_i(request),
    .requested_current_floor_i(current_floor),
    .requested_destination_floor_i(destination_floor),
    .floor_o(elevator_current_floor),
    .direction_o(elevator_direction),
    .request_served_o(ready)
);


initial begin
    $dumpfile("elevator.vcd");
    $dumpvars(0, elevator_tb);

    #(500*CLOCKPERIOD);
    $finish(0);
end

endmodule

elevator_logic/elevator.vcd
$date
	Tue Jan 27 21:06:18 2026
$end
$version
	Icarus Verilog
$end
$timescale
	1ps
$end
$scope module elevator_tb $end
$var wire 1 ! ready $end
$var wire 2 " elevator_direction [1:0] $end
$var wire 4 # elevator_current_floor [3:0] $end
$var parameter 32 $ CLOCKPERIOD $end
$var parameter 32 % MAXFLOORS $end
$var parameter 32 & MINFLOORS $end
$var reg 1 ' clk_i $end
$var reg 4 ( current_floor [3:0] $end
$var reg 4 ) destination_floor [3:0] $end
$var reg 1 * request $end
$var reg 1 + rst_i $end
$scope module elevator_uut $end
$var wire 1 ' clk_i $end
$var wire 1 * request_i $end
$var wire 4 , requested_current_floor_i [3:0] $end
$var wire 4 - requested_destination_floor_i [3:0] $end
$var wire 1 + rst_i $end
$var parameter 2 . GOING_DOWN $end
$var parameter 2 / GOING_UP $end
$var parameter 32 0 MAXFLOORS $end
$var parameter 32 1 MINFLOORS $end
$var parameter 33 2 N_FLOORS $end
$var parameter 2 3 STATIONARY $end
$var reg 4 4 current_floor [3:0] $end
$var reg 2 5 direction_o [1:0] $end
$var reg 4 6 floor_o [3:0] $end
$var reg 10 7 pressed_buttons [9:0] $end
$var reg 2 8 prev_direction_q0 [1:0] $end
$var reg 2 9 prev_direction_q1 [1:0] $end
$var reg 1 ! request_served_o $end
$var reg 2 : current_state [1:0] $end
$var reg 2 ; next_state [1:0] $end
$scope begin output_block $end
$upscope $end
$scope begin state_update $end
$upscope $end
$upscope $end
$upscope $end
$enddefinitions $end
$comment Show the parameter values. $end
$dumpall
b1 3
b1010 2
b0 1
b1010 0
b11 /
b0 .
b0 &
b1010 %
b1100100 $
$end
#0
$dumpvars
b0 ;
b0 :
bx 9
bx 8
bx 7
bx 6
b1 5
bx 4
bx -
bx ,
0+
x*
bx )
bx (
0'
bx #
b1 "
x!
$end
#50000
b0 #
b0 6
b10 ;
b0 9
b0 8
b0 7
b0 4
1'
#100000
0'
#150000
b0 ;
1'
#200000
0'
#250000
1'
#300000
0'
#350000
1'
#400000
0'
#450000
1'
#500000
0'
#550000
1'
#600000
0'
#650000
1'
#700000
0'
#750000
1'
#800000
0'
#850000
1'
#900000
0'
#950000
1'
#1000000
0'
#1050000
1'
#1100000
0'
#1150000
1'
#1200000
0'
#1250000
1'
#1300000
0'
#1350000
1'
#1400000
0'
#1450000
1'
#1500000
0'
#1550000
1'
#1600000
0'
#1650000
1'
#1700000
0'
#1750000
1'
#1800000
0'
#1850000
1'
#1900000
0'
#1950000
1'
#2000000
0'
#2003000
1+
#2050000
b1 8
1'
#2100000
0'
#2150000
b1 9
1'
#2200000
0'
#2203000
0!
b1 ;
b1000 )
b1000 -
b100 (
b100 ,
1*
#2250000
b11 "
b11 5
b1 :
1'
#2300000
0'
#2350000
b1 #
b1 6
b1 4
b11 8
1'
#2400000
0'
#2450000
b10 #
b10 6
b10 4
b11 9
1'
#2500000
0'
#2550000
b11 #
b11 6
b0 ;
b11 4
1'
#2600000
0'
#2650000
0*
b100 #
b100 6
1!
b1 "
b1 5
b100 4
b0 :
1'
#2700000
0'
#2750000
b1 ;
b1 8
b100000000 7
1'
#2800000
0'
#2850000
0!
b11 "
b11 5
b1 9
b1 :
1'
#2900000
0'
#2950000
b101 #
b101 6
b101 4
b11 8
1'
#3000000
0'
#3050000
b110 #
b110 6
b110 4
b11 9
1'
#3100000
0'
#3150000
b111 #
b111 6
b0 ;
b111 4
1'
#3200000
0'
#3250000
b1000 #
b1000 6
b1 "
b1 5
b1000 4
b0 :
b0 ;
b0 7
1'
#3300000
0'
#3350000
b1 8
1'
#3400000
0'
#3450000
b1 9
1'
