elevator_logic/ElevatorLogic.sv
module ElevatorLogic #(
    parameter MAXFLOORS = 10,
    parameter MINFLOORS = 0,
    parameter N_FLOORS = MAXFLOORS-MINFLOORS
) (
    input logic clk_i,
    input logic rst_i,
    input logic[N_FLOORS-1:0] request_down_i,
    input logic[N_FLOORS-1:0] request_up_i,
    input logic[3:0] requested_floor_i,
    output logic[3:0] floor_o,
    output logic[1:0] direction_o,
    output logic request_served_o
);

localparam GOING_UP = 2'b11;
localparam GOING_DOWN = 2'b00;
localparam STATIONARY = 2'b01;

typedef enum bit[1:0] {state_stationary=2'b00, state_up=2'b10, state_down=2'b01} state_t;
state_t current_state, next_state;
logic[3:0] current_floor;
logic[N_FLOORS-1:0] pressed_buttons;
logic[N_FLOORS-1:0] floor_enc;
logic active_request;

always_ff @(posedge clk_i) begin 
    if (rst_i == 1'b0) begin
        current_floor <= '0;
        current_state <= state_stationary;
        next_state <= state_stationary;
        active_request <= 1'b1;
        pressed_buttons <= '0;
        floor_enc <= '0;
    end else begin
        current_state <= next_state;
        
        // latching request
        active_request <= request_down_i[current_floor] || request_up_i[current_floor];
        
        // handling button presses
        if (pressed_buttons[current_floor] == 1'b1 && current_state == state_stationary) begin // button is de-pressed once the person steps out of the elevator.
            pressed_buttons[current_floor] = 1'b0;
        end else if (active_request && current_state == state_stationary) begin // button is pressed only when person enters the elevator.
            pressed_buttons[requested_floor_i] <= 1'b1;
        end else pressed_buttons <= pressed_buttons;

        // current_floor manipulations. Considering next_state to compensate for clk delay
        if (next_state == state_stationary) current_floor <= current_floor;
        else if (next_state == state_up) current_floor <= current_floor + 1'd1;
        else  current_floor <= current_floor - 1'd1;

        // floor encoding (shift registers)
        for(int k = 0; k < N_FLOORS; k++) begin
            if(k == current_floor) floor_enc[k] <= 1'b1;
            else floor_enc[k] <= 1'b0;
        end
    end
end

always_comb begin : state_update
    case (current_state)
        state_stationary : begin
            if (|(pressed_buttons) == 1'b0 && |(request_up_i) == 1'b0 && |(request_down_i) == 1'b0) begin // there are no pressed button and new no requests made
                next_state = state_stationary;
            end else if (|(pressed_buttons) == 1'b0 && |(request_up_i) == 1'b1 && |(request_down_i) == 1'b0) begin // there is new request to go up
                if (floor_enc > request_up_i) next_state = state_down;
                else if (floor_enc < request_up_i) next_state = state_up;
                else next_state = state_stationary;                
            end else if (|(pressed_buttons) == 1'b0 && |(request_up_i) == 1'b0 && |(request_down_i) == 1'b1) begin // there is new request to go down
                if (floor_enc > request_down_i) next_state = state_down;
                else if (floor_enc < request_down_i) next_state = state_up;
                else next_state = state_stationary;
            end else if ((|(pressed_buttons) == 1'b1 && pressed_buttons[current_floor] == 1'b0 && request_up_i[current_floor] == 1'b0 && request_down_i[current_floor] == 1'b0)) begin // there is/are pending requests and no new requests.
                if (floor_enc > pressed_buttons) next_state = state_down;
                else if (floor_enc < pressed_buttons) next_state = state_up;
                else next_state = state_stationary; // there are new and pending request. wait for new request to be registered.
            end
        end
        state_up : begin
            // Currently going up.
            // Go to stationary iff:
            // 1) there is a button pressed (destination reached). 2) ADDITIONAL UP request is received on the way up. 3) a NEW DOWN request is received.
            if (pressed_buttons[current_floor] == 1'b1 || request_up_i[current_floor] == 1'b1 || (request_down_i[current_floor]) == 1'b1 && |(pressed_buttons) == 1'b0 ) begin
                next_state = state_stationary;
            end else next_state = state_up;
        end
        state_down : begin
            // Currently going down.
            // Go to stationary iff:
            // 1) there is a button pressed (destination reached). 2) ADDITIONAL DOWN request is received on the way up. 3) a NEW UP request is received.
            if (pressed_buttons[current_floor] == 1'b1 || request_down_i[current_floor] == 1'b1 || (request_up_i[current_floor]) == 1'b1 && |(pressed_buttons) == 1'b0) begin
                next_state = state_stationary;
            end else next_state = state_down;
        end
        default: 
            next_state = state_stationary;
    endcase
    
end

always_comb begin : output_block
    request_served_o = ((request_down_i[current_floor] == 1'b1 || request_up_i[current_floor] == 1'b1) && pressed_buttons[requested_floor_i] == 1'b1) ? 1'b1 : 1'b0;
    case(current_state)
        state_stationary : begin
            direction_o = STATIONARY;
            floor_o = current_floor;
        end
        state_up : begin
            direction_o = GOING_UP;
            floor_o = current_floor;
        end
        state_down : begin
            direction_o = GOING_DOWN;
            floor_o = current_floor;
        end
        default : begin
            direction_o = STATIONARY;
            floor_o = current_floor;
        end
    endcase
end



endmodule

elevator_logic/elevator_tb.sv
`timescale 1ns/1ps
`default_nettype none

module elevator_tb();

localparam CLOCKPERIOD = 100;
localparam MAXFLOORS = 10;
localparam MINFLOORS = 0;
localparam N_FLOORS = MAXFLOORS-MINFLOORS;

logic clk_i,rst_i;
logic[3:0] destination_floor, elevator_current_floor;
logic[1:0] elevator_direction;
logic ready;
logic[N_FLOORS-1:0] request_down, request_up;

initial clk_i = 1'b0;
initial rst_i = 1'b0;

always #(CLOCKPERIOD/2) clk_i = ~clk_i;

initial begin
    #(20*CLOCKPERIOD + 3);
    rst_i = 1'b1;
end

initial begin
    request_down = '0;
    request_up = '0;
    wait(rst_i);
        // REQ: 4 -> 8
        #(CLOCKPERIOD);
        request_up[4] = 1'b1;
        destination_floor = 4'd8;
        wait(ready);
            #(CLOCKPERIOD);
            request_up = '0;
       
        // REQ: 2 -> 9
        #(CLOCKPERIOD);
        request_up[2] = 1'b1;
        destination_floor = 4'd9;
        wait(ready);
            #(CLOCKPERIOD);
            request_up = '0;
        
        // REQ: 9 -> 2
        #(CLOCKPERIOD);
        request_down[9] = 1'b1;
        destination_floor = 4'd2;
        wait(ready);
            #(CLOCKPERIOD);
            request_down = '0;
        // Additional REQ : 6 -> 3
        #(CLOCKPERIOD);
        request_down[6] = 1'b1;
        destination_floor = 4'd3;
        wait(ready);
            #(CLOCKPERIOD);
            request_down = '0;

        // REQ: 2 -> 9
        #(CLOCKPERIOD);
        request_up[2] = 1'b1;
        destination_floor = 4'd9;
        wait(ready);
            #(CLOCKPERIOD);
            request_up = '0;
        // Additional REQ : 3 -> 6
        #(CLOCKPERIOD);
        request_up[3] = 1'b1;
        destination_floor = 4'd6;
        wait(ready);
            #(CLOCKPERIOD);
            request_up = '0;
end

ElevatorLogic #(
    .MAXFLOORS( MAXFLOORS   ),
    .MINFLOORS( MINFLOORS   )
) elevator_uut (
    .clk_i,
    .rst_i,
    .request_down_i     ( request_down              ),
    .request_up_i       ( request_up                ),
    .requested_floor_i  ( destination_floor         ),
    .floor_o            ( elevator_current_floor    ),
    .direction_o        ( elevator_direction        ),
    .request_served_o   ( ready                     )
);


initial begin
    $dumpfile("elevator.vcd");
    $dumpvars(0, elevator_tb);

    #(500*CLOCKPERIOD);
    $finish(0);
end

endmodule

elevator_logic/elevator.vcd
$date
	Wed Jan 28 19:18:59 2026
$end
$version
	Icarus Verilog
$end
$timescale
	1ps
$end
$scope module elevator_tb $end
$var wire 1 ! ready $end
$var wire 2 " elevator_direction [1:0] $end
$var wire 4 # elevator_current_floor [3:0] $end
$var parameter 32 $ CLOCKPERIOD $end
$var parameter 32 % MAXFLOORS $end
$var parameter 32 & MINFLOORS $end
$var parameter 33 ' N_FLOORS $end
$var reg 1 ( clk_i $end
$var reg 4 ) destination_floor [3:0] $end
$var reg 10 * request_down [9:0] $end
$var reg 10 + request_up [9:0] $end
$var reg 1 , rst_i $end
$scope module elevator_uut $end
$var wire 1 ( clk_i $end
$var wire 10 - request_down_i [9:0] $end
$var wire 10 . request_up_i [9:0] $end
$var wire 4 / requested_floor_i [3:0] $end
$var wire 1 , rst_i $end
$var parameter 2 0 GOING_DOWN $end
$var parameter 2 1 GOING_UP $end
$var parameter 32 2 MAXFLOORS $end
$var parameter 32 3 MINFLOORS $end
$var parameter 33 4 N_FLOORS $end
$var parameter 2 5 STATIONARY $end
$var reg 1 6 active_request $end
$var reg 4 7 current_floor [3:0] $end
$var reg 2 8 direction_o [1:0] $end
$var reg 10 9 floor_enc [9:0] $end
$var reg 4 : floor_o [3:0] $end
$var reg 10 ; pressed_buttons [9:0] $end
$var reg 1 ! request_served_o $end
$var reg 2 < current_state [1:0] $end
$var reg 2 = next_state [1:0] $end
$scope begin $ivl_for_loop0 $end
$var integer 32 > k [31:0] $end
$upscope $end
$scope begin output_block $end
$upscope $end
$scope begin state_update $end
$upscope $end
$upscope $end
$upscope $end
$enddefinitions $end
$comment Show the parameter values. $end
$dumpall
b1 5
b1010 4
b0 3
b1010 2
b11 1
b0 0
b1010 '
b0 &
b1010 %
b1100100 $
$end
#0
$dumpvars
b0 >
b0 =
b0 <
bx ;
bx :
bx 9
b1 8
bx 7
x6
bx /
b0 .
b0 -
0,
b0 +
b0 *
bx )
0(
bx #
b1 "
x!
$end
#50000
b0 #
b0 :
0!
b0 9
b0 ;
16
b0 7
1(
#100000
0(
#150000
1(
#200000
0(
#250000
1(
#300000
0(
#350000
1(
#400000
0(
#450000
1(
#500000
0(
#550000
1(
#600000
0(
#650000
1(
#700000
0(
#750000
1(
#800000
0(
#850000
1(
#900000
0(
#950000
1(
#1000000
0(
#1050000
1(
#1100000
0(
#1150000
1(
#1200000
0(
#1250000
1(
#1300000
0(
#1350000
1(
#1400000
0(
#1450000
1(
#1500000
0(
#1550000
1(
#1600000
0(
#1650000
1(
#1700000
0(
#1750000
1(
#1800000
0(
#1850000
1(
#1900000
0(
#1950000
1(
#2000000
0(
#2003000
1,
#2050000
b1 9
06
b1010 >
1(
#2100000
0(
#2103000
b10 =
b1000 )
b1000 /
b10000 +
b10000 .
#2150000
b1 #
b1 :
b11 "
b11 8
b1 7
b10 <
b1010 >
1(
#2200000
0(
#2250000
b10 #
b10 :
b10 9
b10 7
b1010 >
1(
#2300000
0(
#2350000
b11 #
b11 :
b100 9
b11 7
b1010 >
1(
#2400000
0(
#2450000
b100 #
b100 :
b0 =
b1000 9
b100 7
b1010 >
1(
#2500000
0(
#2550000
b1 "
b1 8
b10000 9
16
b0 <
b1010 >
1(
#2600000
0(
#2650000
1!
b100000000 ;
b1010 >
1(
#2700000
0(
#2750000
b101 #
b101 :
b11 "
b11 8
b101 7
06
b10 <
b1010 >
0!
b10 =
1(
b0 +
b0 .
#2800000
0(
#2850000
b110 #
b110 :
b100000 9
b110 7
b1010 >
1(
b1001 )
b1001 /
b100 +
b100 .
#2900000
0(
#2950000
b111 #
b111 :
b1000000 9
b111 7
b1010 >
1(
#3000000
0(
#3050000
b1000 #
b1000 :
b0 =
b10000000 9
b1000 7
b1010 >
1(
#3100000
0(
#3150000
b1 "
b1 8
b100000000 9
b0 <
b1010 >
1(
#3200000
0(
#3250000
b1 =
b1010 >
b0 ;
1(
#3300000
0(
#3350000
b111 #
b111 :
b0 "
b0 8
b111 7
b1 <
b1010 >
1(
#3400000
0(
#3450000
b110 #
b110 :
b10000000 9
b110 7
b1010 >
1(
#3500000
0(
#3550000
b101 #
b101 :
b1000000 9
b101 7
b1010 >
1(
#3600000
0(
#3650000
b100 #
b100 :
b100000 9
b100 7
b1010 >
1(
#3700000
0(
#3750000
b11 #
b11 :
b10000 9
b11 7
b1010 >
1(
#3800000
0(
#3850000
b10 #
b10 :
b0 =
b1000 9
b10 7
b1010 >
1(
#3900000
0(
#3950000
b1 "
b1 8
b100 9
16
b0 <
b1010 >
1(
#4000000
0(
#4050000
1!
b1000000000 ;
b1010 >
1(
#4100000
0(
#4150000
b11 #
b11 :
b11 "
b11 8
b11 7
06
b10 <
b1010 >
0!
b10 =
1(
b0 +
b0 .
#4200000
0(
#4250000
b100 #
b100 :
b1000 9
b100 7
b1010 >
1(
b10 )
b10 /
b1000000000 *
b1000000000 -
#4300000
0(
#4350000
b101 #
b101 :
b10000 9
b101 7
b1010 >
1(
#4400000
0(
#4450000
b110 #
b110 :
b100000 9
b110 7
b1010 >
1(
#4500000
0(
#4550000
b111 #
b111 :
b1000000 9
b111 7
b1010 >
1(
#4600000
0(
#4650000
b1000 #
b1000 :
b10000000 9
b1000 7
b1010 >
1(
#4700000
0(
#4750000
b1001 #
b1001 :
b0 =
b100000000 9
b1001 7
b1010 >
1(
#4800000
0(
#4850000
b1 "
b1 8
b1000000000 9
16
b0 <
b1010 >
1(
#4900000
0(
#4950000
b1010 >
b0 ;
1(
#5000000
0(
#5050000
1!
b100 ;
b1010 >
1(
#5100000
0(
#5150000
b1000 #
b1000 :
b0 "
b0 8
b1000 7
06
b1 <
b1010 >
0!
b1 =
1(
b0 *
b0 -
#5200000
0(
#5250000
b111 #
b111 :
b100000000 9
b111 7
b1010 >
1(
b11 )
b11 /
b1000000 *
b1000000 -
#5300000
0(
#5350000
b110 #
b110 :
b0 =
b10000000 9
b110 7
b1010 >
1(
#5400000
0(
#5450000
b1 "
b1 8
b1000000 9
16
b0 <
b1010 >
1(
#5500000
0(
#5550000
1!
b1100 ;
b1010 >
1(
#5600000
0(
#5650000
b101 #
b101 :
b0 "
b0 8
b101 7
06
b1 <
b1010 >
0!
b1 =
1(
b0 *
b0 -
#5700000
0(
#5750000
b100 #
b100 :
b100000 9
b100 7
b1010 >
1(
b1001 )
b1001 /
b100 +
b100 .
#5800000
0(
#5850000
b11 #
b11 :
b0 =
b10000 9
b11 7
b1010 >
1(
#5900000
0(
#5950000
b1 "
b1 8
b1000 9
b0 <
b1010 >
1(
#6000000
0(
#6050000
b1 =
b1010 >
b100 ;
1(
#6100000
0(
#6150000
b10 #
b10 :
b0 "
b0 8
b0 =
b10 7
b1 <
b1010 >
1(
#6200000
0(
#6250000
b1 "
b1 8
b100 9
16
b0 <
b1010 >
1(
#6300000
0(
#6350000
b1010 >
b0 ;
1(
#6400000
0(
#6450000
1!
b1000000000 ;
b1010 >
1(
#6500000
0(
#6550000
b11 #
b11 :
b11 "
b11 8
b11 7
06
b10 <
b1010 >
0!
b10 =
1(
b0 +
b0 .
#6600000
0(
#6650000
b1 "
b1 8
b1000 9
16
b0 <
b1010 >
b0 =
1(
b110 )
b110 /
b1000 +
b1000 .
#6700000
0(
#6750000
1!
b1001000000 ;
b1010 >
1(
#6800000
0(
#6850000
b100 #
b100 :
b11 "
b11 8
b100 7
06
b10 <
b1010 >
0!
b10 =
1(
b0 +
b0 .
#6900000
0(
#6950000
b101 #
b101 :
b10000 9
b101 7
b1010 >
1(
#7000000
0(
#7050000
b110 #
b110 :
b0 =
b100000 9
b110 7
b1010 >
1(
#7100000
0(
#7150000
b1 "
b1 8
b1000000 9
b0 <
b1010 >
1(
#7200000
0(
#7250000
b10 =
b1010 >
b1000000000 ;
1(
#7300000
0(
#7350000
b111 #
b111 :
b11 "
b11 8
b111 7
b10 <
b1010 >
1(
#7400000
0(
#7450000
b1000 #
b1000 :
b10000000 9
b1000 7
b1010 >
1(
#7500000
0(
#7550000
b1001 #
b1001 :
b0 =
b100000000 9
b1001 7
b1010 >
1(
#7600000
0(
#7650000
b1 "
b1 8
b1000000000 9
b0 <
b1010 >
1(
#7700000
0(
#7750000
b1010 >
b0 ;
1(
#7800000
0(
#7850000
b1010 >
1(
#7900000
0(
#7950000
b1010 >
1(
#8000000
0(
#8050000
b1010 >
1(
#8100000
0(
#8150000
b1010 >
1(
#8200000
0(
#8250000
b1010 >
1(
#8300000
0(
#8350000
b1010 >
1(
#8400000
0(
#8450000
b1010 >
1(
#8500000
0(
#8550000
b1010 >
1(
#8600000
0(
#8650000
b1010 >
1(
#8700000
0(
#8750000
b1010 >
1(
#8800000
0(
#8850000
b1010 >
1(
#8900000
0(
#8950000
b1010 >
1(
#9000000
0(
#9050000
b1010 >
1(
#9100000
0(
#9150000
b1010 >
1(
#9200000
0(
#9250000
b1010 >
1(
#9300000
0(
#9350000
b1010 >
1(
#9400000
0(
#9450000
b1010 >
1(
#9500000
0(
#9550000
b1010 >
1(
#9600000
0(
#9650000
b1010 >
1(
#9700000
0(
#9750000
b1010 >
1(
#9800000
0(
#9850000
b1010 >
1(
#9900000
0(
#9950000
b1010 >
1(
#10000000
0(
#10050000
b1010 >
1(
#10100000
0(
#10150000
b1010 >
1(
#10200000
0(
#10250000
b1010 >
1(
#10300000
0(
#10350000
b1010 >
1(
#10400000
0(
#10450000
b1010 >
1(
#10500000
0(
#10550000
b1010 >
1(
#10600000
0(
#10650000
b1010 >
1(
#10700000
0(
#10750000
b1010 >
1(
#10800000
0(
#10850000
b1010 >
1(
#10900000
0(
#10950000
b1010 >
1(
#11000000
0(
#11050000
b1010 >
1(
#11100000
0(
#11150000
b1010 >
1(
#11200000
0(
#11250000
b1010 >
1(
#11300000
0(
#11350000
b1010 >
1(
#11400000
0(
#11450000
b1010 >
1(
#11500000
0(
#11550000
b1010 >
1(
#11600000
0(
#11650000
b1010 >
1(
#11700000
0(
#11750000
b1010 >
1(
#11800000
0(
#11850000
b1010 >
1(
#11900000
0(
#11950000
b1010 >
1(
#12000000
0(
#12050000
b1010 >
1(
#12100000
0(
#12150000
b1010 >
1(
#12200000
0(
#12250000
b1010 >
1(
#12300000
0(
#12350000
b1010 >
1(
#12400000
0(
#12450000
b1010 >
1(
#12500000
0(
#12550000
b1010 >
1(
#12600000
0(
#12650000
b1010 >
1(
#12700000
0(
#12750000
b1010 >
1(
#12800000
0(
#12850000
b1010 >
1(
#12900000
0(
#12950000
b1010 >
1(
#13000000
0(
#13050000
b1010 >
1(
#13100000
0(
#13150000
b1010 >
1(
#13200000
0(
#13250000
b1010 >
1(
#13300000
0(
#13350000
b1010 >
1(
#13400000
0(
#13450000
b1010 >
1(
#13500000
0(
#13550000
b1010 >
1(
#13600000
0(
#13650000
b1010 >
1(
#13700000
0(
#13750000
b1010 >
1(
#13800000
0(
#13850000
b1010 >
1(
#13900000
0(
#13950000
b1010 >
1(
#14000000
0(
#14050000
b1010 >
1(
#14100000
0(
#14150000
b1010 >
1(
#14200000
0(
#14250000
b1010 >
1(
#14300000
0(
#14350000
b1010 >
1(
#14400000
0(
#14450000
b1010 >
1(
#14500000
0(
#14550000
b1010 >
1(
#14600000
0(
#14650000
b1010 >
1(
#14700000
0(
#14750000
b1010 >
1(
#14800000
0(
#14850000
b1010 >
1(
#14900000
0(
#14950000
b1010 >
1(
#15000000
0(
#15050000
b1010 >
1(
#15100000
0(
#15150000
b1010 >
1(
#15200000
0(
#15250000
b1010 >
1(
#15300000
0(
#15350000
b1010 >
1(
#15400000
0(
#15450000
b1010 >
1(
#15500000
0(
#15550000
b1010 >
1(
#15600000
0(
#15650000
b1010 >
1(
#15700000
0(
#15750000
b1010 >
1(
#15800000
0(
#15850000
b1010 >
1(
#15900000
0(
#15950000
b1010 >
1(
#16000000
0(
#16050000
b1010 >
1(
#16100000
0(
#16150000
b1010 >
1(
#16200000
0(
#16250000
b1010 >
1(
#16300000
0(
#16350000
b1010 >
1(
#16400000
0(
#16450000
b1010 >
1(
#16500000
0(
#16550000
b1010 >
1(
#16600000
0(
#16650000
b1010 >
1(
#16700000
0(
#16750000
b1010 >
1(
#16800000
0(
#16850000
b1010 >
1(
#16900000
0(
#16950000
b1010 >
1(
#17000000
0(
#17050000
b1010 >
1(
#17100000
0(
#17150000
b1010 >
1(
#17200000
0(
#17250000
b1010 >
1(
#17300000
0(
#17350000
b1010 >
1(
#17400000
0(
#17450000
b1010 >
1(
#17500000
0(
#17550000
b1010 >
1(
#17600000
0(
#17650000
b1010 >
1(
#17700000
0(
#17750000
b1010 >
1(
#17800000
0(
#17850000
b1010 >
1(
#17900000
0(
#17950000
b1010 >
1(
#18000000
0(
#18050000
b1010 >
1(
#18100000
0(
#18150000
b1010 >
1(
#18200000
0(
#18250000
b1010 >
1(
#18300000
0(
#18350000
b1010 >
1(
#18400000
0(
#18450000
b1010 >
1(
#18500000
0(
#18550000
b1010 >
1(
#18600000
0(
#18650000
b1010 >
1(
#18700000
0(
#18750000
b1010 >
1(
#18800000
0(
#18850000
b1010 >
1(
#18900000
0(
#18950000
b1010 >
1(
#19000000
0(
#19050000
b1010 >
1(
#19100000
0(
#19150000
b1010 >
1(
#19200000
0(
#19250000
b1010 >
1(
#19300000
0(
#19350000
b1010 >
1(
#19400000
0(
#19450000
b1010 >
1(
#19500000
0(
#19550000
b1010 >
1(
#19600000
0(
#19650000
b1010 >
1(
#19700000
0(
#19750000
b1010 >
1(
#19800000
0(
#19850000
b1010 >
1(
#19900000
0(
#19950000
b1010 >
1(
#20000000
0(
#20050000
b1010 >
1(
#20100000
0(
#20150000
b1010 >
1(
#20200000
0(
#20250000
b1010 >
1(
#20300000
0(
#20350000
b1010 >
1(
#20400000
0(
#20450000
b1010 >
1(
#20500000
0(
#20550000
b1010 >
1(
#20600000
0(
#20650000
b1010 >
1(
#20700000
0(
#20750000
b1010 >
1(
#20800000
0(
#20850000
b1010 >
1(
#20900000
0(
#20950000
b1010 >
1(
#21000000
0(
#21050000
b1010 >
1(
#21100000
0(
#21150000
b1010 >
1(
#21200000
0(
#21250000
b1010 >
1(
#21300000
0(
#21350000
b1010 >
1(
#21400000
0(
#21450000
b1010 >
1(
#21500000
0(
#21550000
b1010 >
1(
#21600000
0(
#21650000
b1010 >
1(
#21700000
0(
#21750000
b1010 >
1(
#21800000
0(
#21850000
b1010 >
1(
#21900000
0(
#21950000
b1010 >
1(
#22000000
0(
#22050000
b1010 >
1(
#22100000
0(
#22150000
b1010 >
1(
#22200000
0(
#22250000
b1010 >
1(
#22300000
0(
#22350000
b1010 >
1(
#22400000
0(
#22450000
b1010 >
1(
#22500000
0(
#22550000
b1010 >
1(
#22600000
0(
#22650000
b1010 >
1(
#22700000
0(
#22750000
b1010 >
1(
#22800000
0(
#22850000
b1010 >
1(
#22900000
0(
#22950000
b1010 >
1(
#23000000
0(
#23050000
b1010 >
1(
#23100000
0(
#23150000
b1010 >
1(
#23200000
0(
#23250000
b1010 >
1(
#23300000
0(
#23350000
b1010 >
1(
#23400000
0(
#23450000
b1010 >
1(
#23500000
0(
#23550000
b1010 >
1(
#23600000
0(
#23650000
b1010 >
1(
#23700000
0(
#23750000
b1010 >
1(
#23800000
0(
#23850000
b1010 >
1(
#23900000
0(
#23950000
b1010 >
1(
#24000000
0(
#24050000
b1010 >
1(
#24100000
0(
#24150000
b1010 >
1(
#24200000
0(
#24250000
b1010 >
1(
#24300000
0(
#24350000
b1010 >
1(
#24400000
0(
#24450000
b1010 >
1(
#24500000
0(
#24550000
b1010 >
1(
#24600000
0(
#24650000
b1010 >
1(
#24700000
0(
#24750000
b1010 >
1(
#24800000
0(
#24850000
b1010 >
1(
#24900000
0(
#24950000
b1010 >
1(
#25000000
0(
#25050000
b1010 >
1(
#25100000
0(
#25150000
b1010 >
1(
#25200000
0(
#25250000
b1010 >
1(
#25300000
0(
#25350000
b1010 >
1(
#25400000
0(
#25450000
b1010 >
1(
#25500000
0(
#25550000
b1010 >
1(
#25600000
0(
#25650000
b1010 >
1(
#25700000
0(
#25750000
b1010 >
1(
#25800000
0(
#25850000
b1010 >
1(
#25900000
0(
#25950000
b1010 >
1(
#26000000
0(
#26050000
b1010 >
1(
#26100000
0(
#26150000
b1010 >
1(
#26200000
0(
#26250000
b1010 >
1(
#26300000
0(
#26350000
b1010 >
1(
#26400000
0(
#26450000
b1010 >
1(
#26500000
0(
#26550000
b1010 >
1(
#26600000
0(
#26650000
b1010 >
1(
#26700000
0(
#26750000
b1010 >
1(
#26800000
0(
#26850000
b1010 >
1(
#26900000
0(
#26950000
b1010 >
1(
#27000000
0(
#27050000
b1010 >
1(
#27100000
0(
#27150000
b1010 >
1(
#27200000
0(
#27250000
b1010 >
1(
#27300000
0(
#27350000
b1010 >
1(
#27400000
0(
#27450000
b1010 >
1(
#27500000
0(
#27550000
b1010 >
1(
#27600000
0(
#27650000
b1010 >
1(
#27700000
0(
#27750000
b1010 >
1(
#27800000
0(
#27850000
b1010 >
1(
#27900000
0(
#27950000
b1010 >
1(
#28000000
0(
#28050000
b1010 >
1(
#28100000
0(
#28150000
b1010 >
1(
#28200000
0(
#28250000
b1010 >
1(
#28300000
0(
#28350000
b1010 >
1(
#28400000
0(
#28450000
b1010 >
1(
#28500000
0(
#28550000
b1010 >
1(
#28600000
0(
#28650000
b1010 >
1(
#28700000
0(
#28750000
b1010 >
1(
#28800000
0(
#28850000
b1010 >
1(
#28900000
0(
#28950000
b1010 >
1(
#29000000
0(
#29050000
b1010 >
1(
#29100000
0(
#29150000
b1010 >
1(
#29200000
0(
#29250000
b1010 >
1(
#29300000
0(
#29350000
b1010 >
1(
#29400000
0(
#29450000
b1010 >
1(
#29500000
0(
#29550000
b1010 >
1(
#29600000
0(
#29650000
b1010 >
1(
#29700000
0(
#29750000
b1010 >
1(
#29800000
0(
#29850000
b1010 >
1(
#29900000
0(
#29950000
b1010 >
1(
#30000000
0(
#30050000
b1010 >
1(
#30100000
0(
#30150000
b1010 >
1(
#30200000
0(
#30250000
b1010 >
1(
#30300000
0(
#30350000
b1010 >
1(
#30400000
0(
#30450000
b1010 >
1(
#30500000
0(
#30550000
b1010 >
1(
#30600000
0(
#30650000
b1010 >
1(
#30700000
0(
#30750000
b1010 >
1(
#30800000
0(
#30850000
b1010 >
1(
#30900000
0(
#30950000
b1010 >
1(
#31000000
0(
#31050000
b1010 >
1(
#31100000
0(
#31150000
b1010 >
1(
#31200000
0(
#31250000
b1010 >
1(
#31300000
0(
#31350000
b1010 >
1(
#31400000
0(
#31450000
b1010 >
1(
#31500000
0(
#31550000
b1010 >
1(
#31600000
0(
#31650000
b1010 >
1(
#31700000
0(
#31750000
b1010 >
1(
#31800000
0(
#31850000
b1010 >
1(
#31900000
0(
#31950000
b1010 >
1(
#32000000
0(
#32050000
b1010 >
1(
#32100000
0(
#32150000
b1010 >
1(
#32200000
0(
#32250000
b1010 >
1(
#32300000
0(
#32350000
b1010 >
1(
#32400000
0(
#32450000
b1010 >
1(
#32500000
0(
#32550000
b1010 >
1(
#32600000
0(
#32650000
b1010 >
1(
#32700000
0(
#32750000
b1010 >
1(
#32800000
0(
#32850000
b1010 >
1(
#32900000
0(
#32950000
b1010 >
1(
#33000000
0(
#33050000
b1010 >
1(
#33100000
0(
#33150000
b1010 >
1(
#33200000
0(
#33250000
b1010 >
1(
#33300000
0(
#33350000
b1010 >
1(
#33400000
0(
#33450000
b1010 >
1(
#33500000
0(
#33550000
b1010 >
1(
#33600000
0(
#33650000
b1010 >
1(
#33700000
0(
#33750000
b1010 >
1(
#33800000
0(
#33850000
b1010 >
1(
#33900000
0(
#33950000
b1010 >
1(
#34000000
0(
#34050000
b1010 >
1(
#34100000
0(
#34150000
b1010 >
1(
#34200000
0(
#34250000
b1010 >
1(
#34300000
0(
#34350000
b1010 >
1(
#34400000
0(
#34450000
b1010 >
1(
#34500000
0(
#34550000
b1010 >
1(
#34600000
0(
#34650000
b1010 >
1(
#34700000
0(
#34750000
b1010 >
1(
#34800000
0(
#34850000
b1010 >
1(
#34900000
0(
#34950000
b1010 >
1(
#35000000
0(
#35050000
b1010 >
1(
#35100000
0(
#35150000
b1010 >
1(
#35200000
0(
#35250000
b1010 >
1(
#35300000
0(
#35350000
b1010 >
1(
#35400000
0(
#35450000
b1010 >
1(
#35500000
0(
#35550000
b1010 >
1(
#35600000
0(
#35650000
b1010 >
1(
#35700000
0(
#35750000
b1010 >
1(
#35800000
0(
#35850000
b1010 >
1(
#35900000
0(
#35950000
b1010 >
1(
#36000000
0(
#36050000
b1010 >
1(
#36100000
0(
#36150000
b1010 >
1(
#36200000
0(
#36250000
b1010 >
1(
#36300000
0(
#36350000
b1010 >
1(
#36400000
0(
#36450000
b1010 >
1(
#36500000
0(
#36550000
b1010 >
1(
#36600000
0(
#36650000
b1010 >
1(
#36700000
0(
#36750000
b1010 >
1(
#36800000
0(
#36850000
b1010 >
1(
#36900000
0(
#36950000
b1010 >
1(
#37000000
0(
#37050000
b1010 >
1(
#37100000
0(
#37150000
b1010 >
1(
#37200000
0(
#37250000
b1010 >
1(
#37300000
0(
#37350000
b1010 >
1(
#37400000
0(
#37450000
b1010 >
1(
#37500000
0(
#37550000
b1010 >
1(
#37600000
0(
#37650000
b1010 >
1(
#37700000
0(
#37750000
b1010 >
1(
#37800000
0(
#37850000
b1010 >
1(
#37900000
0(
#37950000
b1010 >
1(
#38000000
0(
#38050000
b1010 >
1(
#38100000
0(
#38150000
b1010 >
1(
#38200000
0(
#38250000
b1010 >
1(
#38300000
0(
#38350000
b1010 >
1(
#38400000
0(
#38450000
b1010 >
1(
#38500000
0(
#38550000
b1010 >
1(
#38600000
0(
#38650000
b1010 >
1(
#38700000
0(
#38750000
b1010 >
1(
#38800000
0(
#38850000
b1010 >
1(
#38900000
0(
#38950000
b1010 >
1(
#39000000
0(
#39050000
b1010 >
1(
#39100000
0(
#39150000
b1010 >
1(
#39200000
0(
#39250000
b1010 >
1(
#39300000
0(
#39350000
b1010 >
1(
#39400000
0(
#39450000
b1010 >
1(
#39500000
0(
#39550000
b1010 >
1(
#39600000
0(
#39650000
b1010 >
1(
#39700000
0(
#39750000
b1010 >
1(
#39800000
0(
#39850000
b1010 >
1(
#39900000
0(
#39950000
b1010 >
1(
#40000000
0(
#40050000
b1010 >
1(
#40100000
0(
#40150000
b1010 >
1(
#40200000
0(
#40250000
b1010 >
1(
#40300000
0(
#40350000
b1010 >
1(
#40400000
0(
#40450000
b1010 >
1(
#40500000
0(
#40550000
b1010 >
1(
#40600000
0(
#40650000
b1010 >
1(
#40700000
0(
#40750000
b1010 >
1(
#40800000
0(
#40850000
b1010 >
1(
#40900000
0(
#40950000
b1010 >
1(
#41000000
0(
#41050000
b1010 >
1(
#41100000
0(
#41150000
b1010 >
1(
#41200000
0(
#41250000
b1010 >
1(
#41300000
0(
#41350000
b1010 >
1(
#41400000
0(
#41450000
b1010 >
1(
#41500000
0(
#41550000
b1010 >
1(
#41600000
0(
#41650000
b1010 >
1(
#41700000
0(
#41750000
b1010 >
1(
#41800000
0(
#41850000
b1010 >
1(
#41900000
0(
#41950000
b1010 >
1(
