parzen_window/triangle.sv
`default_nettype none

module triangle #(
    parameter SIZE_POW2 = 10,
    parameter MIN = 0
) (
    input logic clk_i,
    input logic rst_i,
    output logic [SIZE_POW2-1:0] val_o
);

localparam MAX = 2**(SIZE_POW2-1);
logic f_top, f_bottom, f_up, f_down;

always_ff @(posedge clk_i) begin : flag_toggle
    if (rst_i == 1'b0) begin
        f_top <= '0;
        f_bottom <= '0;
        f_up <= '0;
        f_down <= '0;
    end
    else begin
        f_top <= (val_o == MAX - 2) ? 1'b1 : 1'b0;
        f_bottom <= (val_o == MIN + 2) ? 1'b1 : 1'b0; // gives one unwanted pulse after rester, but not harmful.
       
        if (f_up == 1'b0 && f_top == 1'b0 && f_bottom == 1'b0 && f_down == 1'b0) begin // After reset, go up
            f_up <= 1'b1;
            f_down <= 1'b0;
        end else if (f_up == 1'b1 && f_top == 1'b1) begin // reached max, go down
            f_up <= 1'b0;
            f_down <= 1'b1;
        end else if (f_down == 1'b1 && f_bottom == 1'b1) begin // reached min go up
            f_up <= 1'b1;
            f_down <= 1'b0;
        end else begin
            f_up <= f_up;
            f_down <= f_down;
        end

    end
end

always_ff @(posedge clk_i) begin : counter_blk
    if (rst_i == 1'b0) begin
        val_o <= '0;
    end else begin
        if (f_up == 1'b1) begin
            val_o <= val_o + 'd1;
        end else if (f_down == 1'b1) begin
            val_o <= val_o - 'd1;
        end else begin
            val_o <= val_o;
        end
    end
end
    
endmodule

parzen_window/ParzenWindow_NP.sv
`default_nettype none

module ParzenWindow_NP #(
    parameter WINDOW_SIZE_POW2 = 10,
    parameter INTERNAL_FRAC = 16,
    parameter OUTPUT_INT = 10, 
    parameter OUTPUT_FRAC = 16
) (
    input logic clk_i,
    input logic rst_i,
    input logic[WINDOW_SIZE_POW2-1:0] tri_i,
    output logic[OUTPUT_INT-1:-OUTPUT_FRAC] win_o
);

localparam B_INT = WINDOW_SIZE_POW2;
localparam B2_INT = B_INT + B_INT;
localparam B3_INT = B2_INT + B_INT;
localparam B_SCALE_INT = B_INT + 3;

localparam B_FRAC = INTERNAL_FRAC;
localparam B2_FRAC = B_FRAC + B_FRAC;
localparam B3_FRAC = B2_FRAC + B_FRAC;
localparam B_SCALE_FRAC = B_FRAC;

logic[B_INT-1:-B_FRAC] abs_n;
logic[B_INT-1:-B_FRAC] b;
logic[B2_INT-1:-B2_FRAC] b2;
logic[B3_INT-1:-B3_FRAC] b3;

logic[B_SCALE_INT-1:-B_SCALE_FRAC] c6b1;
logic[B_SCALE_INT-1:-B_SCALE_FRAC] c6b2;
logic[B_SCALE_INT-1:-B_SCALE_FRAC] c6b3;
logic[B_SCALE_INT-1:-B_SCALE_FRAC] c2b3;

logic[B_INT-1:-B_FRAC] one_constant;
logic[B_INT-1:-B_FRAC] two_constant;

logic[B_INT-1:-B_FRAC] f1;
logic[B_INT-1:-B_FRAC] f2;

assign abs_n[B_INT-1:0] = tri_i;
assign abs_n[-1:-B_FRAC] = '0;

assign b = abs_n >> (WINDOW_SIZE_POW2-1);
assign b2 = b*b; 
assign b3 = b2*b; 

assign c6b1 = b*6;
assign c6b2 = b2[B_INT-1:-B_FRAC]*6;
assign c6b3 = b3[B_INT-1:-B_FRAC]*6;
assign c2b3 = b3[B_INT-1:-B_FRAC]*2;

assign one_constant[B_INT-1:0] = 1;
assign one_constant[-1:-B_FRAC] = '0;

assign two_constant[B_INT-1:0] = 2;
assign two_constant[-1:-B_FRAC] = '0;

assign f1 = one_constant - c6b2 + c6b3;
assign f2 = two_constant - c6b1 + c6b2 - c2b3;

always_comb begin 
    if (rst_i == 1'b0) begin
        win_o = '0;
    end else begin
        if (tri_i[WINDOW_SIZE_POW2-1:WINDOW_SIZE_POW2-2] > 0) begin
            win_o = f1;
        end else begin
            win_o = f2;
        end
    end
    
end

endmodule

parzen_window/parzen_tb.sv
`timescale 1ns/1ps

module parzen_tb();

localparam CLOCKPERIOD = 100;
localparam SIZE_POW2 = 10;
localparam INTERNAL_FRAC = 16;
localparam OUTPUT_INT = 10;
localparam OUTPUT_FRAC = 16;


logic clk_i;
logic rst_i;
logic [SIZE_POW2-1:0] tri_wave;
logic [OUTPUT_INT-1:-OUTPUT_FRAC] window_output;

initial clk_i = 1'b0;
initial rst_i = 1'b0;

initial begin
    #(10*CLOCKPERIOD);
    rst_i = 1'b1;
end

always begin 
    #(CLOCKPERIOD/2);
    clk_i = ~clk_i;    
end


ParzenWindow_NP #(
    .WINDOW_SIZE_POW2(SIZE_POW2), 
    .INTERNAL_FRAC(INTERNAL_FRAC),
    .OUTPUT_INT(OUTPUT_INT),
    .OUTPUT_FRAC(OUTPUT_FRAC)
    ) parzen_dut (
        .clk_i,
        .rst_i,
        .tri_i(tri_wave),
        .win_o(window_output)
    );

triangle #(
    .SIZE_POW2(SIZE_POW2)
    ) triangle_dut (
    .clk_i,
    .rst_i,
    .val_o(tri_wave)
);

initial begin : vcd_block
    $dumplimit(1048576);  // 1 MB limit
    $dumpfile("parzen_dut.vcd");
    $dumpvars(0, parzen_tb);
end

initial begin : terminate_block
    #(CLOCKPERIOD*2000);
    $finish;
end
endmodule

parzen_window/parzen_dut.vcd
$date
	Tue Jan 20 18:36:12 2026
$end
$version
	Icarus Verilog
$end
$timescale
	1ps
$end
$scope module parzen_tb $end
$var wire 26 ! window_output [9:-16] $end
$var wire 10 " tri_wave [9:0] $end
$var parameter 32 # CLOCKPERIOD $end
$var parameter 32 $ INTERNAL_FRAC $end
$var parameter 32 % OUTPUT_FRAC $end
$var parameter 32 & OUTPUT_INT $end
$var parameter 32 ' SIZE_POW2 $end
$var reg 1 ( clk_i $end
$var reg 1 ) rst_i $end
$scope module parzen_dut $end
$var wire 1 ( clk_i $end
$var wire 1 ) rst_i $end
$var wire 26 * two_constant [9:-16] $end
$var wire 10 + tri_i [9:0] $end
$var wire 26 , one_constant [9:-16] $end
$var wire 26 - f2 [9:-16] $end
$var wire 26 . f1 [9:-16] $end
$var wire 29 / c6b3 [12:-16] $end
$var wire 29 0 c6b2 [12:-16] $end
$var wire 29 1 c6b1 [12:-16] $end
$var wire 29 2 c2b3 [12:-16] $end
$var wire 78 3 b3 [29:-48] $end
$var wire 52 4 b2 [19:-32] $end
$var wire 26 5 b [9:-16] $end
$var wire 26 6 abs_n [9:-16] $end
$var parameter 33 7 B2_FRAC $end
$var parameter 33 8 B2_INT $end
$var parameter 34 9 B3_FRAC $end
$var parameter 34 : B3_INT $end
$var parameter 32 ; B_FRAC $end
$var parameter 32 < B_INT $end
$var parameter 32 = B_SCALE_FRAC $end
$var parameter 33 > B_SCALE_INT $end
$var parameter 32 ? INTERNAL_FRAC $end
$var parameter 32 @ OUTPUT_FRAC $end
$var parameter 32 A OUTPUT_INT $end
$var parameter 32 B WINDOW_SIZE_POW2 $end
$var reg 26 C win_o [9:-16] $end
$upscope $end
$scope module triangle_dut $end
$var wire 1 ( clk_i $end
$var wire 1 ) rst_i $end
$var parameter 32 D MAX $end
$var parameter 32 E MIN $end
$var parameter 32 F SIZE_POW2 $end
$var reg 1 G f_bottom $end
$var reg 1 H f_down $end
$var reg 1 I f_top $end
$var reg 1 J f_up $end
$var reg 10 K val_o [9:0] $end
$scope begin counter_blk $end
$upscope $end
$scope begin flag_toggle $end
$upscope $end
$upscope $end
$scope begin terminate_block $end
$upscope $end
$scope begin vcd_block $end
$upscope $end
$upscope $end
$enddefinitions $end
$comment Show the parameter values. $end
$dumpall
b1010 F
b0 E
b1000000000 D
b1010 B
b1010 A
b10000 @
b10000 ?
b1101 >
b10000 =
b1010 <
b10000 ;
b11110 :
b110000 9
b10100 8
b100000 7
b1010 '
b1010 &
b10000 %
b10000 $
b1100100 #
$end
#0
$dumpvars
bx K
xJ
xI
xH
xG
b0 C
bx0000000000000000 6
b0xxxxxxxxxx0000000 5
bx 4
bx 3
bx 2
bx 1
bx 0
bx /
bx .
bx -
b10000000000000000 ,
bx +
b100000000000000000 *
0)
0(
bx "
b0 !
$end
#50000
b10000000000000000 .
b100000000000000000 -
b0 /
b0 2
b0 0
b0 3
b0 4
b0 1
b0 5
b0 6
b0 "
b0 +
b0 K
0H
0J
0G
0I
1(
#100000
0(
#150000
1(
#200000
0(
#250000
1(
#300000
0(
#350000
1(
#400000
0(
#450000
1(
#500000
0(
#550000
1(
#600000
0(
#650000
1(
#700000
0(
#750000
1(
#800000
0(
#850000
1(
#900000
0(
#950000
1(
#1000000
b100000000000000000 !
b100000000000000000 C
0(
1)
#1050000
1J
1(
#1100000
0(
#1150000
b11111110100000000 !
b11111110100000000 C
b1000000000000000000000 3
b11111110100000000 -
b100000000000000 4
b1100000000 1
b10000000 5
b10000000000000000 6
b1 "
b1 +
b1 K
1(
#1200000
0(
#1250000
b1111111111111010 .
b110 0
b11111101000000110 !
b11111101000000110 C
b11111101000000110 -
b10000000000000000 4
b1000000000000000000000000 3
b11000000000 1
b100000000 5
b100000000000000000 6
b10 "
b10 +
b10 K
1(
#1300000
0(
#1350000
b1111111111110100 .
b1100 0
b11111011100001100 !
b11111011100001100 C
b11111011100001100 -
b100100000000000000 4
b11011000000000000000000000 3
b100100000000 1
b110000000 5
b110000000000000000 6
b11 "
b11 +
b11 K
1G
1(
#1400000
0(
#1450000
b1111111111101000 .
b11000 0
b11111010000011000 !
b11111010000011000 C
b11111010000011000 -
b1000000000000000000 4
b1000000000000000000000000000 3
b110000000000 1
b1000000000 5
b1000000000000000000 6
b100 "
b100 +
b100 K
0G
1(
#1500000
0(
#1550000
b1111111111011100 .
b100100 0
b11111000100100100 !
b11111000100100100 C
b11111000100100100 -
b1100100000000000000 4
b1111101000000000000000000000 3
b111100000000 1
b1010000000 5
b1010000000000000000 6
b101 "
b101 +
b101 K
1(
#1600000
0(
#1650000
b1111111111001010 .
b110110 0
b11110111000110110 !
b11110111000110110 C
b11110111000110110 -
b10010000000000000000 4
b11011000000000000000000000000 3
b1001000000000 1
b1100000000 5
b1100000000000000000 6
b110 "
b110 +
b110 K
1(
#1700000
0(
#1750000
b1111111110111000 .
b1001000 0
b11110101101001000 !
b11110101101001000 C
b11110101101001000 -
b11000100000000000000 4
b101010111000000000000000000000 3
b1010100000000 1
b1110000000 5
b1110000000000000000 6
b111 "
b111 +
b111 K
1(
#1800000
0(
#1850000
b1111111110100000 .
b1100000 0
b11110100001100000 !
b11110100001100000 C
b11110100001100000 -
b100000000000000000000 4
b1000000000000000000000000000000 3
b1100000000000 1
b10000000000 5
b10000000000000000000 6
b1000 "
b1000 +
b1000 K
1(
#1900000
0(
#1950000
b1111111110001000 .
b1111000 0
b11110010101111000 !
b11110010101111000 C
b11110010101111000 -
b101000100000000000000 4
b1011011001000000000000000000000 3
b1101100000000 1
b10010000000 5
b10010000000000000000 6
b1001 "
b1001 +
b1001 K
1(
#2000000
0(
#2050000
b1111111101101010 .
b10010110 0
b11110001010010110 !
b11110001010010110 C
b11110001010010110 -
b110010000000000000000 4
b1111101000000000000000000000000 3
b1111000000000 1
b10100000000 5
b10100000000000000000 6
b1010 "
b1010 +
b1010 K
1(
#2100000
0(
#2150000
b1111111101001100 .
b10110100 0
b11101111110110100 !
b11101111110110100 C
b11101111110110100 -
b111100100000000000000 4
b10100110011000000000000000000000 3
b10000100000000 1
b10110000000 5
b10110000000000000000 6
b1011 "
b1011 +
b1011 K
1(
#2200000
0(
#2250000
b1111111100101000 .
b11011000 0
b11101110011011000 !
b11101110011011000 C
b11101110011011000 -
b1001000000000000000000 4
b11011000000000000000000000000000 3
b10010000000000 1
b11000000000 5
b11000000000000000000 6
b1100 "
b1100 +
b1100 K
1(
#2300000
0(
#2350000
b110 /
b10 2
b1111111100001010 .
b11111100 0
b11101100111111010 !
b11101100111111010 C
b11101100111111010 -
b1010100100000000000000 4
b100010010101000000000000000000000 3
b10011100000000 1
b11010000000 5
b11010000000000000000 6
b1101 "
b1101 +
b1101 K
1(
#2400000
0(
#2450000
b1111111011100000 .
b100100110 0
b11101011100100100 !
b11101011100100100 C
b11101011100100100 -
b1100010000000000000000 4
b101010111000000000000000000000000 3
b10101000000000 1
b11100000000 5
b11100000000000000000 6
b1110 "
b1110 +
b1110 K
1(
#2500000
0(
#2550000
b1111111010110110 .
b101010000 0
b11101010001001110 !
b11101010001001110 C
b11101010001001110 -
b1110000100000000000000 4
b110100101111000000000000000000000 3
b10110100000000 1
b11110000000 5
b11110000000000000000 6
b1111 "
b1111 +
b1111 K
1(
#2600000
0(
#2650000
b1100 /
b100 2
b1111111010001100 .
b110000000 0
b11101000101111100 !
b11101000101111100 C
b11101000101111100 -
b10000000000000000000000 4
b1000000000000000000000000000000000 3
b11000000000000 1
b100000000000 5
b100000000000000000000 6
b10000 "
b10000 +
b10000 K
1(
#2700000
0(
#2750000
b1111111001011100 .
b110110000 0
b11100111010101100 !
b11100111010101100 C
b11100111010101100 -
b10010000100000000000000 4
b1001100110001000000000000000000000 3
b11001100000000 1
b100010000000 5
b100010000000000000000 6
b10001 "
b10001 +
b10001 K
1(
#2800000
0(
#2850000
b1111111000100110 .
b111100110 0
b11100101111100010 !
b11100101111100010 C
b11100101111100010 -
b10100010000000000000000 4
b1011011001000000000000000000000000 3
b11011000000000 1
b100100000000 5
b100100000000000000000 6
b10010 "
b10010 +
b10010 K
1(
#2900000
0(
#2950000
b1111110111110110 .
b1000011100 0
b10010 /
b110 2
b11100100100010110 !
b11100100100010110 C
b11100100100010110 -
b10110100100000000000000 4
b1101011001011000000000000000000000 3
b11100100000000 1
b100110000000 5
b100110000000000000000 6
b10011 "
b10011 +
b10011 K
1(
#3000000
0(
#3050000
b1111110110111010 .
b1001011000 0
b11100011001010010 !
b11100011001010010 C
b11100011001010010 -
b11001000000000000000000 4
b1111101000000000000000000000000000 3
b11110000000000 1
b101000000000 5
b101000000000000000000 6
b10100 "
b10100 +
b10100 K
1(
#3100000
0(
#3150000
b1111110110000100 .
b1010010100 0
b11000 /
b1000 2
b11100001110001100 !
b11100001110001100 C
b11100001110001100 -
b11011100100000000000000 4
b10010000101101000000000000000000000 3
b11111100000000 1
b101010000000 5
b101010000000000000000 6
b10101 "
b10101 +
b10101 K
1(
#3200000
0(
#3250000
b11110 /
b1010 2
b1111110101001000 .
b1011010110 0
b11100000011001100 !
b11100000011001100 C
b11100000011001100 -
b11110010000000000000000 4
b10100110011000000000000000000000000 3
b100001000000000 1
b101100000000 5
b101100000000000000000 6
b10110 "
b10110 +
b10110 K
1(
#3300000
0(
#3350000
b1111110100000110 .
b1100011000 0
b11011111000001110 !
b11011111000001110 C
b11011111000001110 -
b100001000100000000000000 4
b10111110000111000000000000000000000 3
b100010100000000 1
b101110000000 5
b101110000000000000000 6
b10111 "
b10111 +
b10111 K
1(
#3400000
0(
#3450000
b1111110011000100 .
b1101100000 0
b100100 /
b1100 2
b11011101101010100 !
b11011101101010100 C
b11011101101010100 -
b100100000000000000000000 4
b11011000000000000000000000000000000 3
b100100000000000 1
b110000000000 5
b110000000000000000000 6
b11000 "
b11000 +
b11000 K
1(
#3500000
0(
#3550000
b1111110010000010 .
b1110101000 0
b101010 /
b1110 2
b11011100010011010 !
b11011100010011010 C
b11011100010011010 -
b100111000100000000000000 4
b11110100001001000000000000000000000 3
b100101100000000 1
b110010000000 5
b110010000000000000000 6
b11001 "
b11001 +
b11001 K
1(
#3600000
0(
#3650000
b110000 /
b10000 2
b1111110000111010 .
b1111110110 0
b11011010111100110 !
b11011010111100110 C
b11011010111100110 -
b101010010000000000000000 4
b100010010101000000000000000000000000 3
b100111000000000 1
b110100000000 5
b110100000000000000000 6
b11010 "
b11010 +
b11010 K
1(
#3700000
0(
#3750000
b110110 /
b10010 2
b1111101111110010 .
b10001000100 0
b11011001100110010 !
b11011001100110010 C
b11011001100110010 -
b101101100100000000000000 4
b100110011100011000000000000000000000 3
b101000100000000 1
b110110000000 5
b110110000000000000000 6
b11011 "
b11011 +
b11011 K
1(
#3800000
0(
#3850000
b111100 /
b10100 2
b1111101110100100 .
b10010011000 0
b11011000010000100 !
b11011000010000100 C
b11011000010000100 -
b110001000000000000000000 4
b101010111000000000000000000000000000 3
b101010000000000 1
b111000000000 5
b111000000000000000000 6
b11100 "
b11100 +
b11100 K
1(
#3900000
0(
#3950000
b1111101101010110 .
b10011101100 0
b1000010 /
b10110 2
b11010110111010110 !
b11010110111010110 C
b11010110111010110 -
b110100100100000000000000 4
b101111101000101000000000000000000000 3
b101011100000000 1
b111010000000 5
b111010000000000000000 6
b11101 "
b11101 +
b11101 K
1(
#4000000
0(
#4050000
b1111101100001000 .
b10101000110 0
b1001110 /
b11010 2
b11010101100101100 !
b11010101100101100 C
b11010101100101100 -
b111000010000000000000000 4
b110100101111000000000000000000000000 3
b101101000000000 1
b111100000000 5
b111100000000000000000 6
b11110 "
b11110 +
b11110 K
1(
#4100000
0(
#4150000
b1010100 /
b11100 2
b1111101010110100 .
b10110100000 0
b11010100010000100 !
b11010100010000100 C
b11010100010000100 -
b111100000100000000000000 4
b111010001011111000000000000000000000 3
b101110100000000 1
b111110000000 5
b111110000000000000000 6
b11111 "
b11111 +
b11111 K
1(
#4200000
0(
#4250000
b1111101001100000 .
b11000000000 0
b1100000 /
b100000 2
b11010010111100000 !
b11010010111100000 C
b11010010111100000 -
b1000000000000000000000000 4
b1000000000000000000000000000000000000 3
b110000000000000 1
b1000000000000 5
b1000000000000000000000 6
b100000 "
b100000 +
b100000 K
1(
#4300000
0(
#4350000
b1100110 /
b100010 2
b1111101000000110 .
b11001100000 0
b11010001100111110 !
b11010001100111110 C
b11010001100111110 -
b1000100000100000000000000 4
b1000110001100001000000000000000000000 3
b110001100000000 1
b1000010000000 5
b1000010000000000000000 6
b100001 "
b100001 +
b100001 K
1(
#4400000
0(
#4450000
b1111100110101100 .
b11011000110 0
b1110010 /
b100110 2
b11010000010100000 !
b11010000010100000 C
b11010000010100000 -
b1001000010000000000000000 4
b1001100110001000000000000000000000000 3
b110011000000000 1
b1000100000000 5
b1000100000000000000000 6
b100010 "
b100010 +
b100010 K
1(
#4500000
0(
#4550000
b1111000 /
b101000 2
b1111100101001100 .
b11100101100 0
b11001111000000100 !
b11001111000000100 C
b11001111000000100 -
b1001100100100000000000000 4
b1010011101111011000000000000000000000 3
b110100100000000 1
b1000110000000 5
b1000110000000000000000 6
b100011 "
b100011 +
b100011 K
1(
#4600000
0(
#4650000
b1111100011101100 .
b11110011000 0
b10000100 /
b101100 2
b11001101101101100 !
b11001101101101100 C
b11001101101101100 -
b1010001000000000000000000 4
b1011011001000000000000000000000000000 3
b110110000000000 1
b1001000000000 5
b1001000000000000000000 6
b100100 "
b100100 +
b100100 K
1(
#4700000
0(
#4750000
b1111100010001100 .
b100000000100 0
b10010000 /
b110000 2
b11001100011010100 !
b11001100011010100 C
b11001100011010100 -
b1010101100100000000000000 4
b1100010111011101000000000000000000000 3
b110111100000000 1
b1001010000000 5
b1001010000000000000000 6
b100101 "
b100101 +
b100101 K
1(
#4800000
0(
#4850000
b1111100000100110 .
b100001110110 0
b10011100 /
b110100 2
b11001011001000010 !
b11001011001000010 C
b11001011001000010 -
b1011010010000000000000000 4
b1101011001011000000000000000000000000 3
b111001000000000 1
b1001100000000 5
b1001100000000000000000 6
b100110 "
b100110 +
b100110 K
1(
#4900000
0(
#4950000
b1111011111000000 .
b100011101000 0
b10101000 /
b111000 2
b11001001110110000 !
b11001001110110000 C
b11001001110110000 -
b1011111000100000000000000 4
b1110011110110111000000000000000000000 3
b111010100000000 1
b1001110000000 5
b1001110000000000000000 6
b100111 "
b100111 +
b100111 K
1(
#5000000
0(
#5050000
b1111011101011010 .
b100101100000 0
b10111010 /
b111110 2
b11001000100100010 !
b11001000100100010 C
b11001000100100010 -
b1100100000000000000000000 4
b1111101000000000000000000000000000000 3
b111100000000000 1
b1010000000000 5
b1010000000000000000000 6
b101000 "
b101000 +
b101000 K
1(
#5100000
0(
#5150000
b1111011011101110 .
b100111011000 0
b11000110 /
b1000010 2
b11000111010010110 !
b11000111010010110 C
b11000111010010110 -
b1101001000100000000000000 4
b10000110100111001000000000000000000000 3
b111101100000000 1
b1010010000000 5
b1010010000000000000000 6
b101001 "
b101001 +
b101001 K
1(
#5200000
0(
#5250000
b1111011010000010 .
b101001010110 0
b11011000 /
b1001000 2
b11000110000001110 !
b11000110000001110 C
b11000110000001110 -
b1101110010000000000000000 4
b10010000101101000000000000000000000000 3
b111111000000000 1
b1010100000000 5
b1010100000000000000000 6
b101010 "
b101010 +
b101010 K
1(
#5300000
0(
#5350000
b1111011000010000 .
b101011010100 0
b11100100 /
b1001100 2
b11000100110001000 !
b11000100110001000 C
b11000100110001000 -
b1110011100100000000000000 4
b10011011010010011000000000000000000000 3
b1000000100000000 1
b1010110000000 5
b1010110000000000000000 6
b101011 "
b101011 +
b101011 K
1(
#5400000
0(
#5450000
b1111010110011110 .
b101101011000 0
b11110110 /
b1010010 2
b11000011100000110 !
b11000011100000110 C
b11000011100000110 -
b1111001000000000000000000 4
b10100110011000000000000000000000000000 3
b1000010000000000 1
b1011000000000 5
b1011000000000000000000 6
b101100 "
b101100 +
b101100 K
1(
#5500000
0(
#5550000
b1111010100101100 .
b101111011100 0
b100001000 /
b1011000 2
b11000010010000100 !
b11000010010000100 C
b11000010010000100 -
b1111110100100000000000000 4
b10110001111110101000000000000000000000 3
b1000011100000000 1
b1011010000000 5
b1011010000000000000000 6
b101101 "
b101101 +
b101101 K
1(
#5600000
0(
#5650000
b1111010010110100 .
b110001100110 0
b100011010 /
b1011110 2
b11000001000001000 !
b11000001000001000 C
b11000001000001000 -
b10000100010000000000000000 4
b10111110000111000000000000000000000000 3
b1000101000000000 1
b1011100000000 5
b1011100000000000000000 6
b101110 "
b101110 +
b101110 K
1(
#5700000
0(
#5750000
b1111010000111100 .
b110011110000 0
b100101100 /
b1100100 2
b10111111110001100 !
b10111111110001100 C
b10111111110001100 -
b10001010000100000000000000 4
b11001010110001111000000000000000000000 3
b1000110100000000 1
b1011110000000 5
b1011110000000000000000 6
b101111 "
b101111 +
b101111 K
1(
#5800000
0(
#5850000
b1111001111000100 .
b110110000000 0
b101000100 /
b1101100 2
b10111110100010100 !
b10111110100010100 C
b10111110100010100 -
b10010000000000000000000000 4
b11011000000000000000000000000000000000 3
b1001000000000000 1
b1100000000000 5
b1100000000000000000000 6
b110000 "
b110000 +
b110000 K
1(
#5900000
0(
#5950000
b1111001101000110 .
b111000010000 0
b101010110 /
b1110010 2
b10111101010011110 !
b10111101010011110 C
b10111101010011110 -
b10010110000100000000000000 4
b11100101110010001000000000000000000000 3
b1001001100000000 1
b1100010000000 5
b1100010000000000000000 6
b110001 "
b110001 +
b110001 K
1(
#6000000
0(
#6050000
b1111001011001000 .
b111010100110 0
b101101110 /
b1111010 2
b10111100000101100 !
b10111100000101100 C
b10111100000101100 -
b10011100010000000000000000 4
b11110100001001000000000000000000000000 3
b1001011000000000 1
b1100100000000 5
b1100100000000000000000 6
b110010 "
b110010 +
b110010 K
1(
#6100000
0(
#6150000
b1111001001000100 .
b111100111100 0
b110000000 /
b10000000 2
b10111010110111100 !
b10111010110111100 C
b10111010110111100 -
b10100010100100000000000000 4
b100000011000101011000000000000000000000 3
b1001100100000000 1
b1100110000000 5
b1100110000000000000000 6
b110011 "
b110011 +
b110011 K
1(
#6200000
0(
#6250000
b1111000111000000 .
b111111011000 0
b110011000 /
b10001000 2
b10111001101010000 !
b10111001101010000 C
b10111001101010000 -
b10101001000000000000000000 4
b100010010101000000000000000000000000000 3
b1001110000000000 1
b1101000000000 5
b1101000000000000000000 6
b110100 "
b110100 +
b110100 K
1(
#6300000
0(
#6350000
b1111000100111100 .
b1000001110100 0
b110110000 /
b10010000 2
b10111000011100100 !
b10111000011100100 C
b10111000011100100 -
b10101111100100000000000000 4
b100100010110001101000000000000000000000 3
b1001111100000000 1
b1101010000000 5
b1101010000000000000000 6
b110101 "
b110101 +
b110101 K
1(
#6400000
0(
#6450000
b1111000010110010 .
b1000100010110 0
b111001000 /
b10011000 2
b10110111001111110 !
b10110111001111110 C
b10110111001111110 -
b10110110010000000000000000 4
b100110011100011000000000000000000000000 3
b1010001000000000 1
b1101100000000 5
b1101100000000000000000 6
b110110 "
b110110 +
b110110 K
1(
#6500000
0(
#6550000
b1111000000101110 .
b1000110111000 0
b111100110 /
b10100010 2
b10110110000010110 !
b10110110000010110 C
b10110110000010110 -
b10111101000100000000000000 4
b101000100111100111000000000000000000000 3
b1010010100000000 1
b1101110000000 5
b1101110000000000000000 6
b110111 "
b110111 +
b110111 K
1(
#6600000
0(
#6650000
b1110111110011110 .
b1001001100000 0
b111111110 /
b10101010 2
b10110100110110110 !
b10110100110110110 C
b10110100110110110 -
b11000100000000000000000000 4
b101010111000000000000000000000000000000 3
b1010100000000000 1
b1110000000000 5
b1110000000000000000000 6
b111000 "
b111000 +
b111000 K
1(
#6700000
0(
#6750000
b1110111100010100 .
b1001100001000 0
b1000011100 /
b10110100 2
b10110011101010100 !
b10110011101010100 C
b10110011101010100 -
b11001011000100000000000000 4
b101101001101101001000000000000000000000 3
b1010101100000000 1
b1110010000000 5
b1110010000000000000000 6
b111001 "
b111001 +
b111001 K
1(
#6800000
0(
#6850000
b1110111010000100 .
b1001110110110 0
b1000111010 /
b10111110 2
b10110010011111000 !
b10110010011111000 C
b10110010011111000 -
b11010010010000000000000000 4
b101111101000101000000000000000000000000 3
b1010111000000000 1
b1110100000000 5
b1110100000000000000000 6
b111010 "
b111010 +
b111010 K
1(
#6900000
0(
#6950000
b1110110111110100 .
b1010001100100 0
b1001011000 /
b11001000 2
b10110001010011100 !
b10110001010011100 C
b10110001010011100 -
b11011001100100000000000000 4
b110010001001000011000000000000000000000 3
b1011000100000000 1
b1110110000000 5
b1110110000000000000000 6
b111011 "
b111011 +
b111011 K
1(
#7000000
0(
#7050000
b1110110101011110 .
b1010100011000 0
b1001110110 /
b11010010 2
b10110000001000110 !
b10110000001000110 C
b10110000001000110 -
b11100001000000000000000000 4
b110100101111000000000000000000000000000 3
b1011010000000000 1
b1111000000000 5
b1111000000000000000000 6
b111100 "
b111100 +
b111100 K
1(
#7100000
0(
#7150000
b1110110011001000 .
b1010111001100 0
b1010010100 /
b11011100 2
b10101110111110000 !
b10101110111110000 C
b10101110111110000 -
b11101000100100000000000000 4
b110111011010100101000000000000000000000 3
b1011011100000000 1
b1111010000000 5
b1111010000000000000000 6
b111101 "
b111101 +
b111101 K
1(
#7200000
0(
#7250000
b1110110000110010 .
b1011010000110 0
b1010111000 /
b11101000 2
b10101101110011110 !
b10101101110011110 C
b10101101110011110 -
b11110000010000000000000000 4
b111010001011111000000000000000000000000 3
b1011101000000000 1
b1111100000000 5
b1111100000000000000000 6
b111110 "
b111110 +
b111110 K
1(
#7300000
0(
#7350000
b1110101110011100 .
b1011101000000 0
b1011011100 /
b11110100 2
b10101100101001100 !
b10101100101001100 C
b10101100101001100 -
b11111000000100000000000000 4
b111101000010111111000000000000000000000 3
b1011110100000000 1
b1111110000000 5
b1111110000000000000000 6
b111111 "
b111111 +
b111111 K
1(
#7400000
0(
#7450000
b1110101100000000 .
b1100000000000 0
b1100000000 /
b100000000 2
b10101011100000000 !
b10101011100000000 C
b10101011100000000 -
b100000000000000000000000000 4
b1000000000000000000000000000000000000000 3
b1100000000000000 1
b10000000000000 5
b10000000000000000000000 6
b1000000 "
b1000000 +
b1000000 K
1(
#7500000
0(
#7550000
b1110101001100100 .
b1100011000000 0
b1100100100 /
b100001100 2
b10101010010110100 !
b10101010010110100 C
b10101010010110100 -
b100001000000100000000000000 4
b1000011000011000001000000000000000000000 3
b1100001100000000 1
b10000010000000 5
b10000010000000000000000 6
b1000001 "
b1000001 +
b1000001 K
1(
#7600000
0(
#7650000
b1110100111000010 .
b1100110000110 0
b1101001000 /
b100011000 2
b10101001001101110 !
b10101001001101110 C
b10101001001101110 -
b100010000010000000000000000 4
b1000110001100001000000000000000000000000 3
b1100011000000000 1
b10000100000000 5
b10000100000000000000000 6
b1000010 "
b1000010 +
b1000010 K
1(
#7700000
0(
#7750000
b1110100100100000 .
b1101001001100 0
b1101101100 /
b100100100 2
b10101000000101000 !
b10101000000101000 C
b10101000000101000 -
b100011000100100000000000000 4
b1001001011011011011000000000000000000000 3
b1100100100000000 1
b10000110000000 5
b10000110000000000000000 6
b1000011 "
b1000011 +
b1000011 K
1(
#7800000
0(
#7850000
b1110100001111110 .
b1101100011000 0
b1110010110 /
b100110010 2
b10100110111100110 !
b10100110111100110 C
b10100110111100110 -
b100100001000000000000000000 4
b1001100110001000000000000000000000000000 3
b1100110000000000 1
b10001000000000 5
b10001000000000000000000 6
b1000100 "
b1000100 +
b1000100 K
1(
#7900000
0(
#7950000
b1110011111011100 .
b1101111100100 0
b1111000000 /
b101000000 2
b10100101110100100 !
b10100101110100100 C
b10100101110100100 -
b100101001100100000000000000 4
b1010000001100111101000000000000000000000 3
b1100111100000000 1
b10001010000000 5
b10001010000000000000000 6
b1000101 "
b1000101 +
b1000101 K
1(
#8000000
0(
#8050000
b1110011100110100 .
b1110010110110 0
b1111101010 /
b101001110 2
b10100100101101000 !
b10100100101101000 C
b10100100101101000 -
b100110010010000000000000000 4
b1010011101111011000000000000000000000000 3
b1101001000000000 1
b10001100000000 5
b10001100000000000000000 6
b1000110 "
b1000110 +
b1000110 K
1(
#8100000
0(
#8150000
b1110011010001100 .
b1110110001000 0
b10000010100 /
b101011100 2
b10100011100101100 !
b10100011100101100 C
b10100011100101100 -
b100111011000100000000000000 4
b1010111011000010111000000000000000000000 3
b1101010100000000 1
b10001110000000 5
b10001110000000000000000 6
b1000111 "
b1000111 +
b1000111 K
1(
#8200000
0(
